{
  "parse": {
    "title": "G2 Vodafone",
    "pageid": 160832,
    "wikitext": {
      "*": "{{Infobox Team\n|isdisbanded=yes\n|name= G2 Vodafone\n|orgcountry= Spain\n|country=\n|region= Europe\n|image= G2 Vodafonelogo square.png\n|owner= Carlos \"'''ocelote'''\" Rodríguez Santiago \n|headcoach=\n|website= https://www.g2esports.com\n|youtube= https://www.youtube.com/FollowGamers2\n|facebook= https://www.facebook.com/G2esports\n|twitter= G2esports\n|subreddit= G2eSports\n|instagram= g2_vodafone\n|sponsor= [http://www.vodafone.es/ Vodafone]\n|created= 2016-01-17\n|disbanded= \n|trades= \n|rosterphoto= \n}}{{TOCRWI|2}}\n\n'''G2 Vodafone''' is a sister team of [[G2 Esports]] that was created to compete in the Spanish scene.\n\n== History ==\n\n== Timeline ==\n{{TeamNews}}\n\n== Player Roster ==\n<!--===Active===\n{{listplayer/Current/Start|res=yes|dates=yes}}\n{{listplayer/Current/End|}}-->\n\n===Former===\n{{listplayer/Start|newteam=yes|res=yes|dates=yes}}\n{{listplayer|Hero|link=Hero (Miguel Fernández)|es|Miguel Fernández|Jungle|res=EU|newteam=Dragons|joined=2018-01-10|left=2018-04-01}}\n{{listplayer|Nixerino|es|Nicolás Colocho|AD|res=EU|newteam=Dragons|joined=2017-01-02|left=2018-04-01}}\n{{listplayer|Homi|es|Adrián Moldes López|Support|res=EU|newteam=Dragons|joined=2017-11-21|left=2018-04-01}}\n{{listplayer|Siler|es|Ernesto Castañeda|Mid|sub=yes|res=EU|newteam=Penguins|joined=2018-01-11|left=2018-04-01}}\n{{listplayer|Yukinon|es|Eloi García|AD|sub=yes|res=EU|newteam=Dragons E.C.|joined=2018-01-11|left=2018-04-01}}\n{{listplayer|Agresivoo|pl|Tobiasz Ciba|Top|res=EU|newteam=Szata Maga+6|joined=2018-01-10|left=2018-03-30}}\n{{listplayer|Roison|pl|Michał Dubiel|Mid|res=EU|newteam=Szata Maga+6|joined=2018-01-10|left=2018-03-30}}\n{{listplayer|Send0o|es|Rosendo Fuentes|Top|res=EU|sub=yes|newteam=excel|joined=2016-01-16|left=2018-02-06}}\n{{listplayer|Skain|es|David Carbó|Support|sub=yes|res=EU|newteam=Spain5|joined=2016-07-26|left=2018-01-08}}\n{{listplayer|Polyokov|fr|Louis Hamet|Mid|res=EU|newteam=Wind and Rain|joined=2017-08-31|left=2018-01-08}}\n{{listplayer|ElmiilloR|es|Elm Cherto|Jungle|res=EU|sub=yes|newteam=none|joined=2017-08-31}}\n{{listplayer|Chrisberg|dk|Lars Christiansen|AD|res=EU|sub=yes|newteam=FEN1X|joined=2017-08-31|rejoined=yes}}\n{{listplayer|TasteLess|rs|Igor Radusinović|Support|res=EU|sub=yes|newteam=emk|joined=2017-08-31}}\n{{listplayer|Lvsyan|es|Sergi Madrigal|Mid|sub=yes|res=EU|newteam=FEN1X|joined=2017-04-10|left=2018-01-01}}\n{{listplayer|Föur|bg|Stanimir Penchev|Jungle|res=EU|newteam=RIFT Esports|joined=2017-06-12|left=2017-12-01}}\n{{listplayer|Shikari|uk|Jordan Pointon|Top|sub=yes|res=EU|joined=2017-07-??|left=2017-11-??|newteam=Misfits Academy}}\n{{listplayer|Supportive Lion|de|Christos Tsiamis|Support|res=EU|newteam=Team Atlantis (2018 European Team)|joined=2017-08-31|left=2017-10-25}}\n{{listplayer|QTi3|pl|Marcin Pawlak|Jungle|sub=yes|res=EU|newteam=AeQ}}\n{{listplayer|Jinsh|lu|Gilles Chen|Mid|sub=yes|res=EU|newteam=none}}\n{{listplayer|Mourä|es|Melanie Gallardo|Support|sub=yes|res=EU|newteam=none}}\n{{listplayer|ChiQitiN|es|Óscar Alberich|AD|sub=yes|res=EU|newteam=none}}\n{{listplayer|Confysion|dk|Andreas Dalby|Jungle|res=EU|newteam=Atlando|joined=2016-09-20|left=2017-06-09}}\n{{listplayer|Mykilu|es|Juan Antonio Escobar|Top|sub=yes|res=EU|newteam=Movistar Riders}}\n{{listplayer|Galrath|es|Guillermo García|Mid|sub=yes|res=EU|newteam=The Penguins Mafia}}\n{{listplayer|Ninten|es|Yelco Domínguez|Support|sub=yes|res=EU|newteam=ASUS ROG Army}}\n{{listplayer|Swag (Frank Norqvist)|se|Frank Norqvist|Jungle|sub=yes|res=EU|newteam=Team Atlantis}}\n{{listplayer|Siler|es|Ernesto Castañeda|Mid|res=EU|newteam=emonkeyz|joined=2016-11-07|left=2017-04-05}}\n{{listplayer|Chrisberg|dk|Lars Christiansen|AD|res=EU|newteam=gamers origin|joined=2016-09-20|left=2017-01-02}}\n{{listplayer|Epsyle|es|Iago Pallares|Mid|res=EU|newteam=none|joined=2016-04-15|left=2016-11-07}}\n{{listplayer|xTyLk|ua|Jordi Buvalets|Mid|res=EU|newteam=Arctic Gaming|joined=2016-07-29|left=2016-11-01}}\n{{listplayer|InKos|bo|Kevin Alpire|Jungle|res=EU|newteam=LK|joined=2016-01-16|left=2016-09-20}}\n{{listplayer|Sou|es|Guillermo Velasco|AD|res=EU|newteam=LK|joined=2016-01-16|left=2016-09-20}}\n{{listplayer|Miniduke|es|Ismael Martínez|Mid|sub=yes|res=EU|newteam=NeverBack Gaming|joined=2016-01-16|left=2016-09-08}}\n{{listplayer|link=Falco (Jesús Pérez)|Falco|es|Jesús Pérez|Support|res=EU|newteam= Giants Only The Brave|joined=2016-01-16|left=2016-07-26}}\n{{listplayer/End}}\n\n==Organization==\n===Current===\n{{listplayer/Start|staff=yes}}\n{{listplayer|ocelote|es|Carlos Rodríguez Santiago|'''Founder, Owner, & Chief Executive Officer'''}}\n{{listplayersp||de|Jens Hilgers|'''Co-Owner'''}}\n{{listplayersp|z1n0|dk|Jamie Henneberg Bach|'''Chief Operating Officer'''}}\n{{listplayer/End}}\n\n===Former===\n{{listplayer/Start|staff=yes|newteam=yes}}\n{{listplayersp|Lego|es|Jesús García|'''General Manager'''|newteam=Dragons}}\n{{listplayer|Mapache|es|Alex Parejo|'''eSports Director'''|newteam=G2 Esports}}\n{{listplayersp|Nullien|es|María Aranel|'''Staff Coordinator'''|newteam=none}}\n{{listplayer|Furndog|uk|Josh Furneaux|'''Head Coach'''|newteam=xL}}\n{{listplayersp|Garlic|es|Gil González|'''Psychologist'''|newteam=Dragons}}\n{{listplayersp|Swatord|es|David Maraver|'''Psychologist'''|newteam=none}}\n{{listplayersp|Frozenkai|es|Luke Shepard|'''Nutrition Coach'''|newteam=Dragons}}\n{{listplayer|Aagie|es|Carlos Carpio|'''Strategic Coach'''|newteam=Dragons}}\n{{listplayersp|Mushi|au|Kurtis Nicks|'''Strategic Coach'''|newteam=none}}\n{{listplayersp|AleShico|es|Alejandro|'''Scouting/Database'''|newteam=none}}\n{{listplayersp|Bilal|es|Bilal del Valle|'''Analyst'''|newteam=none}}\n{{listplayer|Itachi|es|David Terán|'''Coach'''|newteam=Dark Tigers}}\n{{listplayer|Crazy (Jairo Fariña)|es|Jairo Fariña Mallón|'''Head Analyst'''|newteam=Heretics}}\n{{listplayersp|Manolo|es|Manuel Andrade|'''Analyst'''|newteam=none}}\n{{listplayersp||es|María Jesús|'''Psychologist'''|newteam=none}}\n{{listplayersp||es|Sergio|'''Psychologist'''|newteam=none}}\n{{listplayersp|Sathonyx|es|Adrián Reyes|'''Analyst/Scout'''|newteam=NeverBack Gaming}}\n{{listplayersp|LRojo|es|Lucas Rojo|'''Head Coach'''|newteam=Movistar Riders}}\n{{listplayer|LilSainity|cu|Daniel Fernández|'''Coach'''|newteam=Last Kings}}\n{{listplayer/End}}\n\n== Tournaments ==\n{{TeamResults|show=overviewpage}}\n\n{{TeamShowmatchResults|show=overviewpage}}\n==Interviews==\n\n== Images ==\n<gallery>\nG2 Esports logo red.png|G2 Esports Red Logo\n</gallery>\n\n==External Links==\n\n==References==\n<references />\n\n<br>"
    }
  },
  "_cachedAt": 1778050607874
}