{
  "parse": {
    "title": "Eclypsia.Luna",
    "pageid": 156668,
    "wikitext": {
      "*": "{{Infobox Team|isdisbanded=yes\n|name= Eclypsia.Luna\n|orgcountry= France \n|country=\n|region=EU\n|image=Eclypsia_Logo.png\n|coaches= \n|manager= Marvin '''\"Praec\"''' Stratmann\n|captain= \n|website= http://www.eclypsia.com/en/home.html\n|youtube=\n|facebook=https://www.facebook.com/pages/EC-Luna\n|twitter= \n|irc= \n|sponsor= \n|created= 2012-08-17\n|disbanded= 2012-08-30\n|trades= \n}}{{TOCRWI}}\n\n'''Eclypsia.Luna''' is the second European squad to be formed under the Eclypsia eSports organization, after [[Eclypsia.Solaris]]. The team was created after Eclypsia signed the roster of Team Impact.\n\n== History ==\n== Timeline ==\n{{TeamNews}}\n\n== Player Roster ==\n{{TeamMembersCurrent}}\n===Former===\n{{TeamMembersFormer}}\n\n== Organization ==\n{{listplayer/Start|staff=yes|newteam=yes}}\n{{listplayersp|Praec|de|Marvin Stratmann|'''Manager'''||newteam=Team Solo Mebdi}}\n{{Listplayer/End}}\n\n== Tournaments ==\n{{TeamResults|show=overviewpage}}\n{{TeamShowmatchResults|show=overviewpage}}\n=== As Team Impact ===\n{{TeamResults|Team Impact|show=overviewpage}}\n\n== Highlight Videos ==\n\n==Interviews==\n\n==See Also==\n\n==Links==\n\n==References==\n<references />\n\n<br><!-- -->"
    }
  },
  "_cachedAt": 1778050546978
}