{
  "batchcomplete": "",
  "continue": {
    "eicontinue": "0|730215",
    "continue": "-||"
  },
  "query": {
    "embeddedin": [
      {
        "pageid": 710067,
        "ns": 0,
        "title": "Alexandazar"
      },
      {
        "pageid": 710070,
        "ns": 0,
        "title": "Rule (Antonio Bologna)"
      },
      {
        "pageid": 710079,
        "ns": 0,
        "title": "Flarke"
      },
      {
        "pageid": 710088,
        "ns": 0,
        "title": "Macko (Vicko Mihovilčević)"
      },
      {
        "pageid": 710141,
        "ns": 0,
        "title": "Harbo"
      },
      {
        "pageid": 710149,
        "ns": 0,
        "title": "Peki"
      },
      {
        "pageid": 710155,
        "ns": 0,
        "title": "Spuds"
      },
      {
        "pageid": 710156,
        "ns": 0,
        "title": "Cheviz"
      },
      {
        "pageid": 710157,
        "ns": 0,
        "title": "Bolita"
      },
      {
        "pageid": 710161,
        "ns": 0,
        "title": "Deku (Marco Gamio)"
      },
      {
        "pageid": 710169,
        "ns": 0,
        "title": "Laura Croft"
      },
      {
        "pageid": 710227,
        "ns": 0,
        "title": "Böng (Costa Rican Player)"
      },
      {
        "pageid": 710228,
        "ns": 0,
        "title": "Qu35O"
      },
      {
        "pageid": 710229,
        "ns": 0,
        "title": "Joaco"
      },
      {
        "pageid": 710230,
        "ns": 0,
        "title": "SexFlex"
      },
      {
        "pageid": 710231,
        "ns": 0,
        "title": "Mizzet"
      },
      {
        "pageid": 710266,
        "ns": 0,
        "title": "Gras"
      },
      {
        "pageid": 710277,
        "ns": 0,
        "title": "Acuarelas"
      },
      {
        "pageid": 710278,
        "ns": 0,
        "title": "Trigger (Alfredo Chan)"
      },
      {
        "pageid": 710279,
        "ns": 0,
        "title": "Nilu"
      },
      {
        "pageid": 710280,
        "ns": 0,
        "title": "El Teddy"
      },
      {
        "pageid": 710281,
        "ns": 0,
        "title": "Covenantt"
      },
      {
        "pageid": 710282,
        "ns": 0,
        "title": "Halloween"
      },
      {
        "pageid": 710283,
        "ns": 0,
        "title": "Sun Jeon"
      },
      {
        "pageid": 710284,
        "ns": 0,
        "title": "Kazuya"
      },
      {
        "pageid": 710285,
        "ns": 0,
        "title": "Leafs"
      },
      {
        "pageid": 710287,
        "ns": 0,
        "title": "RkShaka"
      },
      {
        "pageid": 710311,
        "ns": 0,
        "title": "Did"
      },
      {
        "pageid": 710320,
        "ns": 0,
        "title": "Solu"
      },
      {
        "pageid": 710437,
        "ns": 0,
        "title": "COldMemo"
      },
      {
        "pageid": 710464,
        "ns": 0,
        "title": "Anato"
      },
      {
        "pageid": 710468,
        "ns": 0,
        "title": "Rusty (Emanuel Souza)"
      },
      {
        "pageid": 710472,
        "ns": 0,
        "title": "Darn Arne"
      },
      {
        "pageid": 710559,
        "ns": 0,
        "title": "Batuuu"
      },
      {
        "pageid": 710617,
        "ns": 0,
        "title": "Logic (Ge Xu-Chen)"
      },
      {
        "pageid": 710623,
        "ns": 0,
        "title": "Riokkee"
      },
      {
        "pageid": 710626,
        "ns": 0,
        "title": "Timson"
      },
      {
        "pageid": 710629,
        "ns": 0,
        "title": "CedeoCedeo"
      },
      {
        "pageid": 710635,
        "ns": 0,
        "title": "Lycades"
      },
      {
        "pageid": 710638,
        "ns": 0,
        "title": "Rainy"
      },
      {
        "pageid": 710641,
        "ns": 0,
        "title": "Geser"
      },
      {
        "pageid": 710650,
        "ns": 0,
        "title": "Atrocis"
      },
      {
        "pageid": 710659,
        "ns": 0,
        "title": "Rhino (Luca Knödler)"
      },
      {
        "pageid": 710661,
        "ns": 0,
        "title": "Xiaoxia"
      },
      {
        "pageid": 710723,
        "ns": 0,
        "title": "S0bek"
      },
      {
        "pageid": 710727,
        "ns": 0,
        "title": "Brad (Bradley-Norman Virlouvet)"
      },
      {
        "pageid": 710778,
        "ns": 0,
        "title": "Tazad"
      },
      {
        "pageid": 710789,
        "ns": 0,
        "title": "Hashirama"
      },
      {
        "pageid": 710839,
        "ns": 0,
        "title": "Sentherus"
      },
      {
        "pageid": 710852,
        "ns": 0,
        "title": "Brad (Brandon Vicars-Harris)"
      },
      {
        "pageid": 710912,
        "ns": 0,
        "title": "Bloodlust"
      },
      {
        "pageid": 710972,
        "ns": 0,
        "title": "Prcko"
      },
      {
        "pageid": 710977,
        "ns": 0,
        "title": "Doro"
      },
      {
        "pageid": 711000,
        "ns": 0,
        "title": "Casablanca"
      },
      {
        "pageid": 711070,
        "ns": 0,
        "title": "Donny"
      },
      {
        "pageid": 711074,
        "ns": 0,
        "title": "Trilan"
      },
      {
        "pageid": 711078,
        "ns": 0,
        "title": "Unkn0wn5"
      },
      {
        "pageid": 711084,
        "ns": 0,
        "title": "Phraser"
      },
      {
        "pageid": 711218,
        "ns": 0,
        "title": "Ballzy (Greek Player)"
      },
      {
        "pageid": 711337,
        "ns": 0,
        "title": "DailomeR"
      },
      {
        "pageid": 711353,
        "ns": 0,
        "title": "BrokenSoul"
      },
      {
        "pageid": 711356,
        "ns": 0,
        "title": "Electricshoe"
      },
      {
        "pageid": 711361,
        "ns": 0,
        "title": "Despien"
      },
      {
        "pageid": 711364,
        "ns": 0,
        "title": "Redeem"
      },
      {
        "pageid": 711367,
        "ns": 0,
        "title": "Ascended IRL"
      },
      {
        "pageid": 711370,
        "ns": 0,
        "title": "Kaiting"
      },
      {
        "pageid": 711373,
        "ns": 0,
        "title": "Xtract"
      },
      {
        "pageid": 711377,
        "ns": 0,
        "title": "SHXDXW"
      },
      {
        "pageid": 711388,
        "ns": 0,
        "title": "Leonardo"
      },
      {
        "pageid": 711391,
        "ns": 0,
        "title": "BoemiR"
      },
      {
        "pageid": 711394,
        "ns": 0,
        "title": "Caps (Michael Brottrager)"
      },
      {
        "pageid": 711397,
        "ns": 0,
        "title": "Senshi (Samuel Bier)"
      },
      {
        "pageid": 711400,
        "ns": 0,
        "title": "Gumel"
      },
      {
        "pageid": 711403,
        "ns": 0,
        "title": "Why So Obvious"
      },
      {
        "pageid": 711408,
        "ns": 0,
        "title": "Thorax (Austrian Player)"
      },
      {
        "pageid": 711409,
        "ns": 0,
        "title": "Slender"
      },
      {
        "pageid": 711410,
        "ns": 0,
        "title": "Shess"
      },
      {
        "pageid": 711411,
        "ns": 0,
        "title": "Beryll"
      },
      {
        "pageid": 711412,
        "ns": 0,
        "title": "Trinity (Austrian Player)"
      },
      {
        "pageid": 711464,
        "ns": 0,
        "title": "Zero Impact"
      },
      {
        "pageid": 711469,
        "ns": 0,
        "title": "Buddy (Manuel Steiner)"
      },
      {
        "pageid": 711524,
        "ns": 0,
        "title": "Addusto"
      },
      {
        "pageid": 711592,
        "ns": 0,
        "title": "Kuchta"
      },
      {
        "pageid": 711790,
        "ns": 0,
        "title": "Feitann"
      },
      {
        "pageid": 711898,
        "ns": 0,
        "title": "V1tal"
      },
      {
        "pageid": 712093,
        "ns": 0,
        "title": "Invokid"
      },
      {
        "pageid": 712104,
        "ns": 0,
        "title": "Crem"
      },
      {
        "pageid": 712107,
        "ns": 0,
        "title": "Colden"
      },
      {
        "pageid": 712126,
        "ns": 0,
        "title": "Spooder"
      },
      {
        "pageid": 712130,
        "ns": 0,
        "title": "Porcupine"
      },
      {
        "pageid": 712134,
        "ns": 0,
        "title": "Hellman"
      },
      {
        "pageid": 712138,
        "ns": 0,
        "title": "Zoophobias"
      },
      {
        "pageid": 712141,
        "ns": 0,
        "title": "Xero (Victor Kim-Long Hov)"
      },
      {
        "pageid": 712247,
        "ns": 0,
        "title": "Traffi"
      },
      {
        "pageid": 712391,
        "ns": 0,
        "title": "Sinine"
      },
      {
        "pageid": 712413,
        "ns": 0,
        "title": "Ufrock"
      },
      {
        "pageid": 712430,
        "ns": 0,
        "title": "Peop"
      },
      {
        "pageid": 712434,
        "ns": 0,
        "title": "AzizYıldırım"
      },
      {
        "pageid": 712438,
        "ns": 0,
        "title": "Stalken"
      },
      {
        "pageid": 712442,
        "ns": 0,
        "title": "Fynox"
      },
      {
        "pageid": 712445,
        "ns": 0,
        "title": "Gazal"
      },
      {
        "pageid": 712448,
        "ns": 0,
        "title": "Arawn"
      },
      {
        "pageid": 712452,
        "ns": 0,
        "title": "Alfred (Oğuzcan Sarkış)"
      },
      {
        "pageid": 712533,
        "ns": 0,
        "title": "Toco"
      },
      {
        "pageid": 712534,
        "ns": 0,
        "title": "Giiro"
      },
      {
        "pageid": 712535,
        "ns": 0,
        "title": "C1nder"
      },
      {
        "pageid": 712620,
        "ns": 0,
        "title": "Roviz"
      },
      {
        "pageid": 712621,
        "ns": 0,
        "title": "Steve Cook"
      },
      {
        "pageid": 712742,
        "ns": 0,
        "title": "Escalante"
      },
      {
        "pageid": 712778,
        "ns": 0,
        "title": "Messi (Malthe Pedersen)"
      },
      {
        "pageid": 712783,
        "ns": 0,
        "title": "Fitidreng"
      },
      {
        "pageid": 712854,
        "ns": 0,
        "title": "Sha"
      },
      {
        "pageid": 712857,
        "ns": 0,
        "title": "CrowMac"
      },
      {
        "pageid": 712880,
        "ns": 0,
        "title": "Grapes"
      },
      {
        "pageid": 712918,
        "ns": 0,
        "title": "Adasz"
      },
      {
        "pageid": 712987,
        "ns": 0,
        "title": "Urien"
      },
      {
        "pageid": 712990,
        "ns": 0,
        "title": "Wasabi"
      },
      {
        "pageid": 713011,
        "ns": 0,
        "title": "Reuzal"
      },
      {
        "pageid": 713012,
        "ns": 0,
        "title": "Lucking"
      },
      {
        "pageid": 713013,
        "ns": 0,
        "title": "Neeck"
      },
      {
        "pageid": 713015,
        "ns": 0,
        "title": "Guante"
      },
      {
        "pageid": 713016,
        "ns": 0,
        "title": "T4N"
      },
      {
        "pageid": 713127,
        "ns": 0,
        "title": "Excelsis"
      },
      {
        "pageid": 713228,
        "ns": 0,
        "title": "Lari"
      },
      {
        "pageid": 713243,
        "ns": 0,
        "title": "Toppy"
      },
      {
        "pageid": 713246,
        "ns": 0,
        "title": "KnicNicks"
      },
      {
        "pageid": 713266,
        "ns": 0,
        "title": "Midorima"
      },
      {
        "pageid": 713312,
        "ns": 0,
        "title": "Hakai (Laurent Perreault)"
      },
      {
        "pageid": 713321,
        "ns": 0,
        "title": "Naughts"
      },
      {
        "pageid": 713330,
        "ns": 0,
        "title": "Nostalgia (Lee Aung)"
      },
      {
        "pageid": 713333,
        "ns": 0,
        "title": "Kloft"
      },
      {
        "pageid": 713336,
        "ns": 0,
        "title": "Frxg"
      },
      {
        "pageid": 713371,
        "ns": 0,
        "title": "Nappy"
      },
      {
        "pageid": 713381,
        "ns": 0,
        "title": "Zakn7"
      },
      {
        "pageid": 713382,
        "ns": 0,
        "title": "Isaac176"
      },
      {
        "pageid": 713386,
        "ns": 0,
        "title": "Jazu"
      },
      {
        "pageid": 713387,
        "ns": 0,
        "title": "Vikous"
      },
      {
        "pageid": 713388,
        "ns": 0,
        "title": "Mendyn"
      },
      {
        "pageid": 713389,
        "ns": 0,
        "title": "Blanenskey"
      },
      {
        "pageid": 713390,
        "ns": 0,
        "title": "Scarpy"
      },
      {
        "pageid": 713408,
        "ns": 0,
        "title": "Xewix"
      },
      {
        "pageid": 713409,
        "ns": 0,
        "title": "Dzejno"
      },
      {
        "pageid": 713410,
        "ns": 0,
        "title": "Endlave"
      },
      {
        "pageid": 713411,
        "ns": 0,
        "title": "Kvbixyz"
      },
      {
        "pageid": 713412,
        "ns": 0,
        "title": "Siriass"
      },
      {
        "pageid": 713451,
        "ns": 0,
        "title": "Kojima"
      },
      {
        "pageid": 713452,
        "ns": 0,
        "title": "Zakalski"
      },
      {
        "pageid": 713453,
        "ns": 0,
        "title": "Mob Siab"
      },
      {
        "pageid": 713459,
        "ns": 0,
        "title": "Shura (Dustin Le)"
      },
      {
        "pageid": 713463,
        "ns": 0,
        "title": "Daesper"
      },
      {
        "pageid": 713469,
        "ns": 0,
        "title": "JonBiven"
      },
      {
        "pageid": 713472,
        "ns": 0,
        "title": "ArekXander"
      },
      {
        "pageid": 713495,
        "ns": 0,
        "title": "Indig0"
      },
      {
        "pageid": 713498,
        "ns": 0,
        "title": "Moozi"
      },
      {
        "pageid": 713501,
        "ns": 0,
        "title": "TUNDRA (Çağan Orhan)"
      },
      {
        "pageid": 713534,
        "ns": 0,
        "title": "Mickey (Jesse Clemmons)"
      },
      {
        "pageid": 713538,
        "ns": 0,
        "title": "Bencomo"
      },
      {
        "pageid": 713547,
        "ns": 0,
        "title": "Raaay"
      },
      {
        "pageid": 713550,
        "ns": 0,
        "title": "Afeto"
      },
      {
        "pageid": 713562,
        "ns": 0,
        "title": "Hopyn"
      },
      {
        "pageid": 713563,
        "ns": 0,
        "title": "Hiperion"
      },
      {
        "pageid": 713567,
        "ns": 0,
        "title": "Witnesss Me"
      },
      {
        "pageid": 713570,
        "ns": 0,
        "title": "Mimic v9"
      },
      {
        "pageid": 713573,
        "ns": 0,
        "title": "Deathwalker"
      },
      {
        "pageid": 713576,
        "ns": 0,
        "title": "Big Beagle"
      },
      {
        "pageid": 713761,
        "ns": 0,
        "title": "Maxu777"
      },
      {
        "pageid": 713880,
        "ns": 0,
        "title": "Lyfaenia"
      },
      {
        "pageid": 713950,
        "ns": 0,
        "title": "Prince (Lucas Krampitz)"
      },
      {
        "pageid": 713953,
        "ns": 0,
        "title": "Javii"
      },
      {
        "pageid": 713960,
        "ns": 0,
        "title": "Iybc9o2 q"
      },
      {
        "pageid": 713984,
        "ns": 0,
        "title": "Alucard (Christos Spiropoulos)"
      },
      {
        "pageid": 714042,
        "ns": 0,
        "title": "Anitius"
      },
      {
        "pageid": 714078,
        "ns": 0,
        "title": "ImCoinflip"
      },
      {
        "pageid": 714096,
        "ns": 0,
        "title": "Coinflip (Giorgio Sammuri)"
      },
      {
        "pageid": 714225,
        "ns": 0,
        "title": "Worthless"
      },
      {
        "pageid": 714228,
        "ns": 0,
        "title": "Nary"
      },
      {
        "pageid": 714240,
        "ns": 0,
        "title": "Immy"
      },
      {
        "pageid": 714243,
        "ns": 0,
        "title": "Jokerr"
      },
      {
        "pageid": 714251,
        "ns": 0,
        "title": "Emp (Emil Eliasson)"
      },
      {
        "pageid": 714255,
        "ns": 0,
        "title": "Euti"
      },
      {
        "pageid": 714355,
        "ns": 0,
        "title": "Nori"
      },
      {
        "pageid": 714569,
        "ns": 0,
        "title": "Apollonia"
      },
      {
        "pageid": 714759,
        "ns": 0,
        "title": "ZekaS"
      },
      {
        "pageid": 714776,
        "ns": 0,
        "title": "Dizin"
      },
      {
        "pageid": 714777,
        "ns": 0,
        "title": "Morttheus"
      },
      {
        "pageid": 714805,
        "ns": 0,
        "title": "Guiyixiong"
      },
      {
        "pageid": 714980,
        "ns": 0,
        "title": "WAwa (Yan Zi-Jing)"
      },
      {
        "pageid": 714992,
        "ns": 0,
        "title": "Mille"
      },
      {
        "pageid": 715092,
        "ns": 0,
        "title": "Takhisis"
      },
      {
        "pageid": 715093,
        "ns": 0,
        "title": "Winter (Argentinian player)"
      },
      {
        "pageid": 715180,
        "ns": 0,
        "title": "Frenzyy"
      },
      {
        "pageid": 715193,
        "ns": 0,
        "title": "GonDyy"
      },
      {
        "pageid": 715194,
        "ns": 0,
        "title": "Rainn"
      },
      {
        "pageid": 715198,
        "ns": 0,
        "title": "Valerys"
      },
      {
        "pageid": 715211,
        "ns": 0,
        "title": "Zarrix"
      },
      {
        "pageid": 715233,
        "ns": 0,
        "title": "Smirr0r"
      },
      {
        "pageid": 715235,
        "ns": 0,
        "title": "Kalemh"
      },
      {
        "pageid": 715236,
        "ns": 0,
        "title": "Faint"
      },
      {
        "pageid": 715238,
        "ns": 0,
        "title": "Lucadyd"
      },
      {
        "pageid": 715449,
        "ns": 0,
        "title": "Sharvel"
      },
      {
        "pageid": 715478,
        "ns": 0,
        "title": "Ru0"
      },
      {
        "pageid": 715483,
        "ns": 0,
        "title": "Think"
      },
      {
        "pageid": 715503,
        "ns": 0,
        "title": "Siwoo"
      },
      {
        "pageid": 715516,
        "ns": 0,
        "title": "GuanGuan"
      },
      {
        "pageid": 715520,
        "ns": 0,
        "title": "Challita"
      },
      {
        "pageid": 715522,
        "ns": 0,
        "title": "Demito"
      },
      {
        "pageid": 715523,
        "ns": 0,
        "title": "Crossbow"
      },
      {
        "pageid": 715524,
        "ns": 0,
        "title": "Nasher"
      },
      {
        "pageid": 715525,
        "ns": 0,
        "title": "700oxin"
      },
      {
        "pageid": 715551,
        "ns": 0,
        "title": "Impacto"
      },
      {
        "pageid": 715552,
        "ns": 0,
        "title": "Overdoxe"
      },
      {
        "pageid": 715553,
        "ns": 0,
        "title": "Dormilon"
      },
      {
        "pageid": 715554,
        "ns": 0,
        "title": "Ekzaar"
      },
      {
        "pageid": 715555,
        "ns": 0,
        "title": "NeverbyJ1"
      },
      {
        "pageid": 715556,
        "ns": 0,
        "title": "Ractita"
      },
      {
        "pageid": 715557,
        "ns": 0,
        "title": "Messi (Argentinian Player)"
      },
      {
        "pageid": 715558,
        "ns": 0,
        "title": "Pechengo"
      },
      {
        "pageid": 715568,
        "ns": 0,
        "title": "Cthulhu"
      },
      {
        "pageid": 715569,
        "ns": 0,
        "title": "Renguita"
      },
      {
        "pageid": 715570,
        "ns": 0,
        "title": "Jorge Rial"
      },
      {
        "pageid": 715571,
        "ns": 0,
        "title": "Danictord"
      },
      {
        "pageid": 715574,
        "ns": 0,
        "title": "Tishuku"
      },
      {
        "pageid": 715575,
        "ns": 0,
        "title": "Metanoid"
      },
      {
        "pageid": 715582,
        "ns": 0,
        "title": "Asdf16"
      },
      {
        "pageid": 715583,
        "ns": 0,
        "title": "LFiurerl"
      },
      {
        "pageid": 715584,
        "ns": 0,
        "title": "Raffito"
      },
      {
        "pageid": 715632,
        "ns": 0,
        "title": "Dunks"
      },
      {
        "pageid": 715658,
        "ns": 0,
        "title": "Harley Quinn"
      },
      {
        "pageid": 715659,
        "ns": 0,
        "title": "BadFeelings"
      },
      {
        "pageid": 715663,
        "ns": 0,
        "title": "Bl0wtuz"
      },
      {
        "pageid": 715664,
        "ns": 0,
        "title": "Pablizhino"
      },
      {
        "pageid": 715665,
        "ns": 0,
        "title": "NugaARG"
      },
      {
        "pageid": 715666,
        "ns": 0,
        "title": "NEkaton"
      },
      {
        "pageid": 715667,
        "ns": 0,
        "title": "Guarkot"
      },
      {
        "pageid": 715668,
        "ns": 0,
        "title": "Bayus"
      },
      {
        "pageid": 715669,
        "ns": 0,
        "title": "Haxball"
      },
      {
        "pageid": 715732,
        "ns": 0,
        "title": "Tentakai"
      },
      {
        "pageid": 715790,
        "ns": 0,
        "title": "Elijah (Elias Alexandrakis)"
      },
      {
        "pageid": 715804,
        "ns": 0,
        "title": "Elijah (Andreas Brandl)"
      },
      {
        "pageid": 715824,
        "ns": 0,
        "title": "Naka"
      },
      {
        "pageid": 715825,
        "ns": 0,
        "title": "Havok"
      },
      {
        "pageid": 715826,
        "ns": 0,
        "title": "GreyAquila"
      },
      {
        "pageid": 715849,
        "ns": 0,
        "title": "Charbuster"
      },
      {
        "pageid": 715850,
        "ns": 0,
        "title": "Eli (Sergio Jachniuk)"
      },
      {
        "pageid": 715853,
        "ns": 0,
        "title": "CaoPio"
      },
      {
        "pageid": 715886,
        "ns": 0,
        "title": "Wen (Liao Wen-Wei)"
      },
      {
        "pageid": 715891,
        "ns": 0,
        "title": "Liweier"
      },
      {
        "pageid": 715901,
        "ns": 0,
        "title": "Wunai3"
      },
      {
        "pageid": 715906,
        "ns": 0,
        "title": "Rose (Song Wen-Ming)"
      },
      {
        "pageid": 715911,
        "ns": 0,
        "title": "Xiaohanbao"
      },
      {
        "pageid": 715995,
        "ns": 0,
        "title": "Zapdo"
      },
      {
        "pageid": 716006,
        "ns": 0,
        "title": "Aleks"
      },
      {
        "pageid": 716169,
        "ns": 0,
        "title": "Spartan (Alejandro Bestard)"
      },
      {
        "pageid": 716476,
        "ns": 0,
        "title": "Sigan"
      },
      {
        "pageid": 716484,
        "ns": 0,
        "title": "Loanrie"
      },
      {
        "pageid": 716528,
        "ns": 0,
        "title": "Yummy"
      },
      {
        "pageid": 716534,
        "ns": 0,
        "title": "Tong (Li Jiong)"
      },
      {
        "pageid": 716539,
        "ns": 0,
        "title": "Realm"
      },
      {
        "pageid": 716546,
        "ns": 0,
        "title": "Suki (Mo Zi-Peng)"
      },
      {
        "pageid": 716569,
        "ns": 0,
        "title": "Lhyz"
      },
      {
        "pageid": 716575,
        "ns": 0,
        "title": "Feifan"
      },
      {
        "pageid": 716586,
        "ns": 0,
        "title": "Nuo"
      },
      {
        "pageid": 716600,
        "ns": 0,
        "title": "BuLuKaKa"
      },
      {
        "pageid": 716607,
        "ns": 0,
        "title": "Mirror (Zou Zheng)"
      },
      {
        "pageid": 716742,
        "ns": 0,
        "title": "Noodles (Axel Barrientos)"
      },
      {
        "pageid": 716743,
        "ns": 0,
        "title": "Thany"
      },
      {
        "pageid": 716800,
        "ns": 0,
        "title": "Henry (Henry Aylas)"
      },
      {
        "pageid": 716807,
        "ns": 0,
        "title": "Darmer"
      },
      {
        "pageid": 716818,
        "ns": 0,
        "title": "Míkoto Suoh"
      },
      {
        "pageid": 716819,
        "ns": 0,
        "title": "Hoffen"
      },
      {
        "pageid": 716826,
        "ns": 0,
        "title": "Winder"
      },
      {
        "pageid": 716835,
        "ns": 0,
        "title": "Daniel (Daniel Saldaña)"
      },
      {
        "pageid": 716836,
        "ns": 0,
        "title": "Sniper Wolf"
      },
      {
        "pageid": 716837,
        "ns": 0,
        "title": "C0p3"
      },
      {
        "pageid": 716838,
        "ns": 0,
        "title": "Jokers"
      },
      {
        "pageid": 716849,
        "ns": 0,
        "title": "Killua (Carlos Calderón)"
      },
      {
        "pageid": 716850,
        "ns": 0,
        "title": "Kain (Jasiel López)"
      },
      {
        "pageid": 716945,
        "ns": 0,
        "title": "Antcliff"
      },
      {
        "pageid": 717006,
        "ns": 0,
        "title": "Kaine"
      },
      {
        "pageid": 717038,
        "ns": 0,
        "title": "Shaochi"
      },
      {
        "pageid": 717041,
        "ns": 0,
        "title": "Biechi"
      },
      {
        "pageid": 717044,
        "ns": 0,
        "title": "Kerry"
      },
      {
        "pageid": 717081,
        "ns": 0,
        "title": "Kanashimi"
      },
      {
        "pageid": 717155,
        "ns": 0,
        "title": "El Bardo"
      },
      {
        "pageid": 717171,
        "ns": 0,
        "title": "Viki"
      },
      {
        "pageid": 717346,
        "ns": 0,
        "title": "DiGod"
      },
      {
        "pageid": 717351,
        "ns": 0,
        "title": "Domoi"
      },
      {
        "pageid": 717357,
        "ns": 0,
        "title": "LittleIguana"
      },
      {
        "pageid": 717360,
        "ns": 0,
        "title": "Derpaherpa"
      },
      {
        "pageid": 717362,
        "ns": 0,
        "title": "Pdrolo"
      },
      {
        "pageid": 717365,
        "ns": 0,
        "title": "SfMemories"
      },
      {
        "pageid": 717437,
        "ns": 0,
        "title": "Zharless"
      },
      {
        "pageid": 717438,
        "ns": 0,
        "title": "Cachúo"
      },
      {
        "pageid": 717439,
        "ns": 0,
        "title": "S1rCris"
      },
      {
        "pageid": 717443,
        "ns": 0,
        "title": "Gyosoo"
      },
      {
        "pageid": 717445,
        "ns": 0,
        "title": "Niño Rata"
      },
      {
        "pageid": 717446,
        "ns": 0,
        "title": "Newjack"
      },
      {
        "pageid": 717447,
        "ns": 0,
        "title": "Alcaede"
      },
      {
        "pageid": 717448,
        "ns": 0,
        "title": "Kai (Mateo Martínez)"
      },
      {
        "pageid": 717449,
        "ns": 0,
        "title": "DarkDeath"
      },
      {
        "pageid": 717450,
        "ns": 0,
        "title": "Wiggles"
      },
      {
        "pageid": 717451,
        "ns": 0,
        "title": "Artes"
      },
      {
        "pageid": 717452,
        "ns": 0,
        "title": "MyGyo"
      },
      {
        "pageid": 717453,
        "ns": 0,
        "title": "RedDrakez"
      },
      {
        "pageid": 717454,
        "ns": 0,
        "title": "KenshinsWrath"
      },
      {
        "pageid": 717455,
        "ns": 0,
        "title": "Macrophyre"
      },
      {
        "pageid": 717457,
        "ns": 0,
        "title": "Cygnus (Juan Castillo)"
      },
      {
        "pageid": 717493,
        "ns": 0,
        "title": "1ssue"
      },
      {
        "pageid": 717504,
        "ns": 0,
        "title": "WSL"
      },
      {
        "pageid": 717633,
        "ns": 0,
        "title": "Abyss (Lin Po-Reng)"
      },
      {
        "pageid": 717635,
        "ns": 0,
        "title": "Cheng9"
      },
      {
        "pageid": 717687,
        "ns": 0,
        "title": "Luty"
      },
      {
        "pageid": 717855,
        "ns": 0,
        "title": "Natur3"
      },
      {
        "pageid": 717858,
        "ns": 0,
        "title": "Lz (Yang Zi-Li)"
      },
      {
        "pageid": 717861,
        "ns": 0,
        "title": "XieDoDo"
      },
      {
        "pageid": 718153,
        "ns": 0,
        "title": "Roi DEMON"
      },
      {
        "pageid": 718159,
        "ns": 0,
        "title": "Murdoc"
      },
      {
        "pageid": 718160,
        "ns": 0,
        "title": "Kanix"
      },
      {
        "pageid": 718165,
        "ns": 0,
        "title": "Kyo"
      },
      {
        "pageid": 718175,
        "ns": 0,
        "title": "IDrakxo"
      },
      {
        "pageid": 718176,
        "ns": 0,
        "title": "Lanzer"
      },
      {
        "pageid": 718177,
        "ns": 0,
        "title": "Warnder"
      },
      {
        "pageid": 718178,
        "ns": 0,
        "title": "Bomboncito"
      },
      {
        "pageid": 718188,
        "ns": 0,
        "title": "Fottiti"
      },
      {
        "pageid": 718189,
        "ns": 0,
        "title": "Herrscher"
      },
      {
        "pageid": 718448,
        "ns": 0,
        "title": "Zsouaia"
      },
      {
        "pageid": 718450,
        "ns": 0,
        "title": "Kcw"
      },
      {
        "pageid": 718451,
        "ns": 0,
        "title": "Enthralled"
      },
      {
        "pageid": 718521,
        "ns": 0,
        "title": "IMinions"
      },
      {
        "pageid": 718529,
        "ns": 0,
        "title": "Tatu (Pedro Seixas)"
      },
      {
        "pageid": 718547,
        "ns": 0,
        "title": "Naitz"
      },
      {
        "pageid": 718549,
        "ns": 0,
        "title": "Hitsu (Benjamin Avila)"
      },
      {
        "pageid": 718551,
        "ns": 0,
        "title": "Avril"
      },
      {
        "pageid": 718661,
        "ns": 0,
        "title": "EMBAIXADOR"
      },
      {
        "pageid": 718703,
        "ns": 0,
        "title": "Rigel (Đào Văn Tuấn)"
      },
      {
        "pageid": 718708,
        "ns": 0,
        "title": "Hyo"
      },
      {
        "pageid": 718725,
        "ns": 0,
        "title": "Ouzi"
      },
      {
        "pageid": 718732,
        "ns": 0,
        "title": "Playcool"
      },
      {
        "pageid": 718856,
        "ns": 0,
        "title": "Dejan1"
      },
      {
        "pageid": 719083,
        "ns": 0,
        "title": "Niko (Nikola Slaný)"
      },
      {
        "pageid": 719199,
        "ns": 0,
        "title": "Andyincher"
      },
      {
        "pageid": 719227,
        "ns": 0,
        "title": "Wolverene"
      },
      {
        "pageid": 719278,
        "ns": 0,
        "title": "Vuckae"
      },
      {
        "pageid": 719351,
        "ns": 0,
        "title": "Gino (Long Do)"
      },
      {
        "pageid": 719397,
        "ns": 0,
        "title": "N0name"
      },
      {
        "pageid": 719405,
        "ns": 0,
        "title": "Jokah"
      },
      {
        "pageid": 719434,
        "ns": 0,
        "title": "Skypture"
      },
      {
        "pageid": 719483,
        "ns": 0,
        "title": "13arry"
      },
      {
        "pageid": 719537,
        "ns": 0,
        "title": "Sirfliper"
      },
      {
        "pageid": 719538,
        "ns": 0,
        "title": "Duki"
      },
      {
        "pageid": 719539,
        "ns": 0,
        "title": "Diintisor"
      },
      {
        "pageid": 719686,
        "ns": 0,
        "title": "Valria"
      },
      {
        "pageid": 719714,
        "ns": 0,
        "title": "OW"
      },
      {
        "pageid": 719715,
        "ns": 0,
        "title": "Hao (Li Tzu-Hao)"
      },
      {
        "pageid": 719719,
        "ns": 0,
        "title": "Yuk1Jie"
      },
      {
        "pageid": 719738,
        "ns": 0,
        "title": "Milkyway"
      },
      {
        "pageid": 719743,
        "ns": 0,
        "title": "V30"
      },
      {
        "pageid": 719744,
        "ns": 0,
        "title": "Kerr"
      },
      {
        "pageid": 719750,
        "ns": 0,
        "title": "XiaoTian (Zhang Bo-Tian)"
      },
      {
        "pageid": 719766,
        "ns": 0,
        "title": "Yihong"
      },
      {
        "pageid": 719910,
        "ns": 0,
        "title": "Figurative"
      },
      {
        "pageid": 719914,
        "ns": 0,
        "title": "Jaeger1"
      },
      {
        "pageid": 719918,
        "ns": 0,
        "title": "EU Red"
      },
      {
        "pageid": 719927,
        "ns": 0,
        "title": "Attice"
      },
      {
        "pageid": 719928,
        "ns": 0,
        "title": "JDLoL (JD Nueces)"
      },
      {
        "pageid": 719931,
        "ns": 0,
        "title": "BOBtimer"
      },
      {
        "pageid": 719934,
        "ns": 0,
        "title": "Davemon"
      },
      {
        "pageid": 719957,
        "ns": 0,
        "title": "Evanlai"
      },
      {
        "pageid": 719960,
        "ns": 0,
        "title": "Johntheman"
      },
      {
        "pageid": 719973,
        "ns": 0,
        "title": "Sunbeh"
      },
      {
        "pageid": 719976,
        "ns": 0,
        "title": "Shupian (Jacky Li)"
      },
      {
        "pageid": 720038,
        "ns": 0,
        "title": "MyCash"
      },
      {
        "pageid": 720041,
        "ns": 0,
        "title": "Rambo (Ivo Dimitrov)"
      },
      {
        "pageid": 720042,
        "ns": 0,
        "title": "Katy (Kateřina Macháčová)"
      },
      {
        "pageid": 720043,
        "ns": 0,
        "title": "Eriee"
      },
      {
        "pageid": 720044,
        "ns": 0,
        "title": "BunnyV"
      },
      {
        "pageid": 720180,
        "ns": 0,
        "title": "Aksin"
      },
      {
        "pageid": 720183,
        "ns": 0,
        "title": "Niinim"
      },
      {
        "pageid": 720207,
        "ns": 0,
        "title": "Ace (Eagan Gallagher)"
      },
      {
        "pageid": 720314,
        "ns": 0,
        "title": "Samikin"
      },
      {
        "pageid": 720315,
        "ns": 0,
        "title": "Torak"
      },
      {
        "pageid": 720353,
        "ns": 0,
        "title": "Lojaz"
      },
      {
        "pageid": 720476,
        "ns": 0,
        "title": "Lemon (Eduardo Garcia)"
      },
      {
        "pageid": 720512,
        "ns": 0,
        "title": "Dark (Filip Laskowski)"
      },
      {
        "pageid": 720914,
        "ns": 0,
        "title": "Eguto"
      },
      {
        "pageid": 721363,
        "ns": 0,
        "title": "CzarnyPiotruś"
      },
      {
        "pageid": 721370,
        "ns": 0,
        "title": "Bezi"
      },
      {
        "pageid": 721415,
        "ns": 0,
        "title": "V1kk"
      },
      {
        "pageid": 721424,
        "ns": 0,
        "title": "Ackerman (Aissa Ibrahim Aissa)"
      },
      {
        "pageid": 721685,
        "ns": 0,
        "title": "Deliria"
      },
      {
        "pageid": 721716,
        "ns": 0,
        "title": "Nevermind"
      },
      {
        "pageid": 721721,
        "ns": 0,
        "title": "SoldierBird"
      },
      {
        "pageid": 721726,
        "ns": 0,
        "title": "BBA"
      },
      {
        "pageid": 721731,
        "ns": 0,
        "title": "Maunter"
      },
      {
        "pageid": 721807,
        "ns": 0,
        "title": "Cuchi"
      },
      {
        "pageid": 722063,
        "ns": 0,
        "title": "Neyzz"
      },
      {
        "pageid": 722195,
        "ns": 0,
        "title": "AhWood"
      },
      {
        "pageid": 722201,
        "ns": 0,
        "title": "IUBB"
      },
      {
        "pageid": 722202,
        "ns": 0,
        "title": "LokzCM"
      },
      {
        "pageid": 722203,
        "ns": 0,
        "title": "Summoner 1"
      },
      {
        "pageid": 722204,
        "ns": 0,
        "title": "而我不小心"
      },
      {
        "pageid": 722344,
        "ns": 0,
        "title": "Tombarrs"
      },
      {
        "pageid": 722351,
        "ns": 0,
        "title": "Regiment Odinn"
      },
      {
        "pageid": 722554,
        "ns": 0,
        "title": "Caesar Uri"
      },
      {
        "pageid": 722623,
        "ns": 0,
        "title": "Stryth"
      },
      {
        "pageid": 722643,
        "ns": 0,
        "title": "Grasady"
      },
      {
        "pageid": 722722,
        "ns": 0,
        "title": "Baran"
      },
      {
        "pageid": 722780,
        "ns": 0,
        "title": "Leks"
      },
      {
        "pageid": 722783,
        "ns": 0,
        "title": "Tim Shady"
      },
      {
        "pageid": 722788,
        "ns": 0,
        "title": "KeNNetic"
      },
      {
        "pageid": 722793,
        "ns": 0,
        "title": "Astalia"
      },
      {
        "pageid": 722811,
        "ns": 0,
        "title": "Lykki"
      },
      {
        "pageid": 722831,
        "ns": 0,
        "title": "Rakusi"
      },
      {
        "pageid": 722877,
        "ns": 0,
        "title": "Hirohina"
      },
      {
        "pageid": 723120,
        "ns": 0,
        "title": "Thallnoss"
      },
      {
        "pageid": 723148,
        "ns": 0,
        "title": "Diodris"
      },
      {
        "pageid": 723279,
        "ns": 0,
        "title": "Yampozumpo"
      },
      {
        "pageid": 723471,
        "ns": 0,
        "title": "Glon"
      },
      {
        "pageid": 723852,
        "ns": 0,
        "title": "Chan (Jang Chan-ho)"
      },
      {
        "pageid": 723853,
        "ns": 0,
        "title": "Toye (Park Dong-hyun)"
      },
      {
        "pageid": 723854,
        "ns": 0,
        "title": "Dooly"
      },
      {
        "pageid": 723855,
        "ns": 0,
        "title": "Milli"
      },
      {
        "pageid": 723856,
        "ns": 0,
        "title": "Celna"
      },
      {
        "pageid": 723857,
        "ns": 0,
        "title": "Jin (Choi Hyun-jin)"
      },
      {
        "pageid": 723858,
        "ns": 0,
        "title": "Solo (Kim Min-kyun)"
      },
      {
        "pageid": 723859,
        "ns": 0,
        "title": "Najebbi"
      },
      {
        "pageid": 723860,
        "ns": 0,
        "title": "Ncsk"
      },
      {
        "pageid": 723861,
        "ns": 0,
        "title": "Dusk (Lee Jun-gum)"
      },
      {
        "pageid": 724100,
        "ns": 0,
        "title": "Godpillar"
      },
      {
        "pageid": 724105,
        "ns": 0,
        "title": "XHB"
      },
      {
        "pageid": 724176,
        "ns": 0,
        "title": "Hoopa"
      },
      {
        "pageid": 724375,
        "ns": 0,
        "title": "Pillow (Rutger Stouthart)"
      },
      {
        "pageid": 724484,
        "ns": 0,
        "title": "Pavelov"
      },
      {
        "pageid": 724548,
        "ns": 0,
        "title": "Ghoul"
      },
      {
        "pageid": 724604,
        "ns": 0,
        "title": "Akko"
      },
      {
        "pageid": 724639,
        "ns": 0,
        "title": "Jamsu"
      },
      {
        "pageid": 725109,
        "ns": 0,
        "title": "Galers"
      },
      {
        "pageid": 725221,
        "ns": 0,
        "title": "Seraph (Konrad Romanowski)"
      },
      {
        "pageid": 725365,
        "ns": 0,
        "title": "Zxy"
      },
      {
        "pageid": 725508,
        "ns": 0,
        "title": "Radíoactive"
      },
      {
        "pageid": 725746,
        "ns": 0,
        "title": "Reri"
      },
      {
        "pageid": 725905,
        "ns": 0,
        "title": "Fonix (Yuta Takasawa)"
      },
      {
        "pageid": 726108,
        "ns": 0,
        "title": "AIM4"
      },
      {
        "pageid": 726110,
        "ns": 0,
        "title": "Calamity"
      },
      {
        "pageid": 726111,
        "ns": 0,
        "title": "Sunleaf"
      },
      {
        "pageid": 726194,
        "ns": 0,
        "title": "Kozak"
      },
      {
        "pageid": 726231,
        "ns": 0,
        "title": "Koisi"
      },
      {
        "pageid": 726232,
        "ns": 0,
        "title": "Enapon"
      },
      {
        "pageid": 726234,
        "ns": 0,
        "title": "Senmary"
      },
      {
        "pageid": 726244,
        "ns": 0,
        "title": "Dragonblood"
      },
      {
        "pageid": 726249,
        "ns": 0,
        "title": "Syouryu"
      },
      {
        "pageid": 726255,
        "ns": 0,
        "title": "Wataneko"
      },
      {
        "pageid": 726361,
        "ns": 0,
        "title": "Demian"
      },
      {
        "pageid": 726362,
        "ns": 0,
        "title": "Asin"
      },
      {
        "pageid": 726617,
        "ns": 0,
        "title": "Ayu (Andrey Saraiva)"
      },
      {
        "pageid": 726729,
        "ns": 0,
        "title": "Jormag"
      },
      {
        "pageid": 726735,
        "ns": 0,
        "title": "Hoshisora"
      },
      {
        "pageid": 726741,
        "ns": 0,
        "title": "Smeagol (Brecht Allegaert)"
      },
      {
        "pageid": 726798,
        "ns": 0,
        "title": "Arthur0"
      },
      {
        "pageid": 726890,
        "ns": 0,
        "title": "Alix"
      },
      {
        "pageid": 726891,
        "ns": 0,
        "title": "Cio"
      },
      {
        "pageid": 726909,
        "ns": 0,
        "title": "Emyr"
      },
      {
        "pageid": 727504,
        "ns": 0,
        "title": "Ziyou"
      },
      {
        "pageid": 727509,
        "ns": 0,
        "title": "Hoshiyoru"
      },
      {
        "pageid": 727897,
        "ns": 0,
        "title": "Saii"
      },
      {
        "pageid": 728033,
        "ns": 0,
        "title": "Smifi"
      },
      {
        "pageid": 728342,
        "ns": 0,
        "title": "Rexha"
      },
      {
        "pageid": 728478,
        "ns": 0,
        "title": "Danny1018"
      },
      {
        "pageid": 728579,
        "ns": 0,
        "title": "I am John"
      },
      {
        "pageid": 728716,
        "ns": 0,
        "title": "ZeMoller"
      },
      {
        "pageid": 728749,
        "ns": 0,
        "title": "Reina Kiyokawa"
      },
      {
        "pageid": 728799,
        "ns": 0,
        "title": "QrowEmerald"
      },
      {
        "pageid": 728967,
        "ns": 0,
        "title": "Curse (Davide Renz)"
      },
      {
        "pageid": 729197,
        "ns": 0,
        "title": "Boohis"
      },
      {
        "pageid": 729207,
        "ns": 0,
        "title": "Sykko"
      },
      {
        "pageid": 729212,
        "ns": 0,
        "title": "Fool"
      },
      {
        "pageid": 729299,
        "ns": 0,
        "title": "Faetski"
      },
      {
        "pageid": 729341,
        "ns": 0,
        "title": "Cran"
      },
      {
        "pageid": 729344,
        "ns": 0,
        "title": "Sol1XD"
      },
      {
        "pageid": 729347,
        "ns": 0,
        "title": "WildDC"
      },
      {
        "pageid": 729348,
        "ns": 0,
        "title": "Fyrlian"
      },
      {
        "pageid": 729353,
        "ns": 0,
        "title": "Misxxxki"
      },
      {
        "pageid": 729356,
        "ns": 0,
        "title": "Blossom (Spanish Player)"
      },
      {
        "pageid": 729359,
        "ns": 0,
        "title": "JSaito"
      },
      {
        "pageid": 729362,
        "ns": 0,
        "title": "Ocana"
      },
      {
        "pageid": 729535,
        "ns": 0,
        "title": "Coach Dman"
      },
      {
        "pageid": 729536,
        "ns": 0,
        "title": "YellowMoonkey"
      },
      {
        "pageid": 729538,
        "ns": 0,
        "title": "Fornoreason"
      },
      {
        "pageid": 729610,
        "ns": 0,
        "title": "Se6t"
      },
      {
        "pageid": 729703,
        "ns": 0,
        "title": "Basuban"
      },
      {
        "pageid": 729706,
        "ns": 0,
        "title": "Plander"
      },
      {
        "pageid": 729710,
        "ns": 0,
        "title": "Isak"
      },
      {
        "pageid": 729918,
        "ns": 0,
        "title": "Real Homie"
      },
      {
        "pageid": 730044,
        "ns": 0,
        "title": "SYZ (Su Yu-Che)"
      },
      {
        "pageid": 730045,
        "ns": 0,
        "title": "GouGou"
      },
      {
        "pageid": 730046,
        "ns": 0,
        "title": "By1"
      },
      {
        "pageid": 730047,
        "ns": 0,
        "title": "Ivar"
      },
      {
        "pageid": 730187,
        "ns": 0,
        "title": "Erlo"
      },
      {
        "pageid": 730195,
        "ns": 0,
        "title": "Guanch0"
      },
      {
        "pageid": 730198,
        "ns": 0,
        "title": "Regi (Diego Lozano)"
      }
    ]
  },
  "_cachedAt": 1778052907164
}