{
  "name": "LRS Players",
  "description": "LRS - 2026 Season",
  "players": [
    {
      "id": "player-39f7c06f",
      "match_name": "Lac",
      "full_name": "Lac",
      "date_of_birth": "2000-02-25",
      "nationality": "AR",
      "profile_image_url": null,
      "position": "ADC",
      "natural_position": "ADC",
      "alternate_positions": [],
      "attributes": {
        "laning": 57,
        "mechanics": 60,
        "discipline": 58,
        "macro_play": 60,
        "consistency": 60,
        "shotcalling": 56,
        "teamfighting": 59,
        "champion_pool": 55,
        "mental_resilience": 59
      },
      "condition": 100,
      "morale": 100,
      "fitness": 100,
      "team_id": "lrs-malvinas-gaming",
      "traits": [],
      "contract_end": "",
      "wage": 0,
      "market_value": 0,
      "stats": {},
      "career": [],
      "training_focus": null,
      "transfer_listed": false,
      "loan_listed": false,
      "transfer_offers": [],
      "morale_core": {},
      "potential_base": 59,
      "potential_revealed": null,
      "potential_research_started_on": null,
      "potential_research_eta_days": null,
      "champion_training_targets": [],
      "can_be_transferred_until": null
    },
    {
      "id": "player-039330d2",
      "match_name": "iso",
      "full_name": "iso",
      "date_of_birth": "1998-03-15",
      "nationality": "AR",
      "profile_image_url": null,
      "position": "ADC",
      "natural_position": "ADC",
      "alternate_positions": [],
      "attributes": {
        "laning": 54,
        "mechanics": 56,
        "discipline": 53,
        "macro_play": 56,
        "consistency": 56,
        "shotcalling": 52,
        "teamfighting": 56,
        "champion_pool": 52,
        "mental_resilience": 54
      },
      "condition": 100,
      "morale": 100,
      "fitness": 100,
      "team_id": "lrs-seven-dark",
      "traits": [],
      "contract_end": "",
      "wage": 0,
      "market_value": 0,
      "stats": {},
      "career": [],
      "training_focus": null,
      "transfer_listed": false,
      "loan_listed": false,
      "transfer_offers": [],
      "morale_core": {},
      "potential_base": 55,
      "potential_revealed": null,
      "potential_research_started_on": null,
      "potential_research_eta_days": null,
      "champion_training_targets": [],
      "can_be_transferred_until": null
    },
    {
      "id": "player-a9937a5c",
      "match_name": "Renyu",
      "full_name": "Renyu",
      "date_of_birth": "2007-03-19",
      "nationality": "PE",
      "profile_image_url": null,
      "position": "ADC",
      "natural_position": "ADC",
      "alternate_positions": [],
      "attributes": {
        "laning": 56,
        "mechanics": 56,
        "discipline": 56,
        "macro_play": 56,
        "consistency": 56,
        "shotcalling": 52,
        "teamfighting": 56,
        "champion_pool": 53,
        "mental_resilience": 55
      },
      "condition": 100,
      "morale": 100,
      "fitness": 100,
      "team_id": "lrs-tu-pap-esports",
      "traits": [],
      "contract_end": "",
      "wage": 0,
      "market_value": 0,
      "stats": {},
      "career": [],
      "training_focus": null,
      "transfer_listed": false,
      "loan_listed": false,
      "transfer_offers": [],
      "morale_core": {},
      "potential_base": 60,
      "potential_revealed": null,
      "potential_research_started_on": null,
      "potential_research_eta_days": null,
      "champion_training_targets": [],
      "can_be_transferred_until": null
    },
    {
      "id": "player-1c2cb48f",
      "match_name": "Naitz",
      "full_name": "Naitz",
      "date_of_birth": "1998-12-29",
      "nationality": "CL",
      "profile_image_url": null,
      "position": "ADC",
      "natural_position": "ADC",
      "alternate_positions": [],
      "attributes": {
        "laning": 65,
        "mechanics": 63,
        "discipline": 64,
        "macro_play": 65,
        "consistency": 65,
        "shotcalling": 62,
        "teamfighting": 64,
        "champion_pool": 62,
        "mental_resilience": 63
      },
      "condition": 100,
      "morale": 100,
      "fitness": 100,
      "team_id": "lrs-seven-dark",
      "traits": [],
      "contract_end": "",
      "wage": 0,
      "market_value": 0,
      "stats": {},
      "career": [],
      "training_focus": null,
      "transfer_listed": false,
      "loan_listed": false,
      "transfer_offers": [],
      "morale_core": {},
      "potential_base": 65,
      "potential_revealed": null,
      "potential_research_started_on": null,
      "potential_research_eta_days": null,
      "champion_training_targets": [],
      "can_be_transferred_until": null
    },
    {
      "id": "player-3b989f7a",
      "match_name": "Hnb",
      "full_name": "Hnb",
      "date_of_birth": "2000-07-20",
      "nationality": "UY",
      "profile_image_url": null,
      "position": "ADC",
      "natural_position": "ADC",
      "alternate_positions": [],
      "attributes": {
        "laning": 63,
        "mechanics": 64,
        "discipline": 64,
        "macro_play": 63,
        "consistency": 63,
        "shotcalling": 60,
        "teamfighting": 62,
        "champion_pool": 60,
        "mental_resilience": 63
      },
      "condition": 100,
      "morale": 100,
      "fitness": 100,
      "team_id": "lrs-tu-pap-esports",
      "traits": [],
      "contract_end": "",
      "wage": 0,
      "market_value": 0,
      "stats": {},
      "career": [],
      "training_focus": null,
      "transfer_listed": false,
      "loan_listed": false,
      "transfer_offers": [],
      "morale_core": {},
      "potential_base": 63,
      "potential_revealed": null,
      "potential_research_started_on": null,
      "potential_research_eta_days": null,
      "champion_training_targets": [],
      "can_be_transferred_until": null
    },
    {
      "id": "player-0aee4cee",
      "match_name": "Chapters",
      "full_name": "Chapters",
      "date_of_birth": "2006-06-20",
      "nationality": "AR",
      "profile_image_url": null,
      "position": "ADC",
      "natural_position": "ADC",
      "alternate_positions": [],
      "attributes": {
        "laning": 58,
        "mechanics": 59,
        "discipline": 56,
        "macro_play": 59,
        "consistency": 59,
        "shotcalling": 56,
        "teamfighting": 59,
        "champion_pool": 56,
        "mental_resilience": 56
      },
      "condition": 100,
      "morale": 100,
      "fitness": 100,
      "team_id": "lrs-maze-gaming",
      "traits": [],
      "contract_end": "",
      "wage": 0,
      "market_value": 0,
      "stats": {},
      "career": [],
      "training_focus": null,
      "transfer_listed": false,
      "loan_listed": false,
      "transfer_offers": [],
      "morale_core": {},
      "potential_base": 63,
      "potential_revealed": null,
      "potential_research_started_on": null,
      "potential_research_eta_days": null,
      "champion_training_targets": [],
      "can_be_transferred_until": null
    },
    {
      "id": "player-59e7835d",
      "match_name": "Warangelus",
      "full_name": "Warangelus",
      "date_of_birth": "2002-02-02",
      "nationality": "CL",
      "profile_image_url": null,
      "position": "ADC",
      "natural_position": "ADC",
      "alternate_positions": [],
      "attributes": {
        "laning": 66,
        "mechanics": 65,
        "discipline": 66,
        "macro_play": 66,
        "consistency": 66,
        "shotcalling": 62,
        "teamfighting": 66,
        "champion_pool": 63,
        "mental_resilience": 65
      },
      "condition": 100,
      "morale": 100,
      "fitness": 100,
      "team_id": "lrs-the-new-kings",
      "traits": [],
      "contract_end": "",
      "wage": 0,
      "market_value": 0,
      "stats": {},
      "career": [],
      "training_focus": null,
      "transfer_listed": false,
      "loan_listed": false,
      "transfer_offers": [],
      "morale_core": {},
      "potential_base": 68,
      "potential_revealed": null,
      "potential_research_started_on": null,
      "potential_research_eta_days": null,
      "champion_training_targets": [],
      "can_be_transferred_until": null
    },
    {
      "id": "player-c0417640",
      "match_name": "ianshaka",
      "full_name": "ianshaka",
      "date_of_birth": "2007-10-17",
      "nationality": "AR",
      "profile_image_url": null,
      "position": "ADC",
      "natural_position": "ADC",
      "alternate_positions": [],
      "attributes": {
        "laning": 64,
        "mechanics": 64,
        "discipline": 64,
        "macro_play": 64,
        "consistency": 64,
        "shotcalling": 60,
        "teamfighting": 64,
        "champion_pool": 61,
        "mental_resilience": 64
      },
      "condition": 100,
      "morale": 100,
      "fitness": 100,
      "team_id": "lrs-volticons",
      "traits": [],
      "contract_end": "",
      "wage": 0,
      "market_value": 0,
      "stats": {},
      "career": [],
      "training_focus": null,
      "transfer_listed": false,
      "loan_listed": false,
      "transfer_offers": [],
      "morale_core": {},
      "potential_base": 70,
      "potential_revealed": null,
      "potential_research_started_on": null,
      "potential_research_eta_days": null,
      "champion_training_targets": [],
      "can_be_transferred_until": null
    },
    {
      "id": "player-81e0184a",
      "match_name": "Wamu",
      "full_name": "Wamu",
      "date_of_birth": "2001-03-01",
      "nationality": "CL",
      "profile_image_url": null,
      "position": "TOP",
      "natural_position": "TOP",
      "alternate_positions": [],
      "attributes": {
        "laning": 62,
        "mechanics": 66,
        "discipline": 62,
        "macro_play": 65,
        "consistency": 65,
        "shotcalling": 62,
        "teamfighting": 66,
        "champion_pool": 62,
        "mental_resilience": 64
      },
      "condition": 100,
      "morale": 100,
      "fitness": 100,
      "team_id": "lrs-golden-lions",
      "traits": [],
      "contract_end": "",
      "wage": 0,
      "market_value": 0,
      "stats": {},
      "career": [],
      "training_focus": null,
      "transfer_listed": false,
      "loan_listed": false,
      "transfer_offers": [],
      "morale_core": {},
      "potential_base": 67,
      "potential_revealed": null,
      "potential_research_started_on": null,
      "potential_research_eta_days": null,
      "champion_training_targets": [],
      "can_be_transferred_until": null
    },
    {
      "id": "player-6ce2157b",
      "match_name": "Dinastik",
      "full_name": "Dinastik",
      "date_of_birth": "2003-10-20",
      "nationality": "CL",
      "profile_image_url": null,
      "position": "TOP",
      "natural_position": "TOP",
      "alternate_positions": [],
      "attributes": {
        "laning": 65,
        "mechanics": 65,
        "discipline": 63,
        "macro_play": 63,
        "consistency": 65,
        "shotcalling": 62,
        "teamfighting": 62,
        "champion_pool": 61,
        "mental_resilience": 62
      },
      "condition": 100,
      "morale": 100,
      "fitness": 100,
      "team_id": "lrs-seven-dark",
      "traits": [],
      "contract_end": "",
      "wage": 0,
      "market_value": 0,
      "stats": {},
      "career": [],
      "training_focus": null,
      "transfer_listed": false,
      "loan_listed": false,
      "transfer_offers": [],
      "morale_core": {},
      "potential_base": 65,
      "potential_revealed": null,
      "potential_research_started_on": null,
      "potential_research_eta_days": null,
      "champion_training_targets": [],
      "can_be_transferred_until": null
    },
    {
      "id": "player-a86b160e",
      "match_name": "Apoka",
      "full_name": "Apoka",
      "date_of_birth": "2004-11-15",
      "nationality": "AR",
      "profile_image_url": null,
      "position": "JUNGLE",
      "natural_position": "JUNGLE",
      "alternate_positions": [],
      "attributes": {
        "laning": 63,
        "mechanics": 63,
        "discipline": 58,
        "macro_play": 60,
        "consistency": 62,
        "shotcalling": 62,
        "teamfighting": 60,
        "champion_pool": 62,
        "mental_resilience": 60
      },
      "condition": 100,
      "morale": 100,
      "fitness": 100,
      "team_id": "lrs-9z-globant",
      "traits": [],
      "contract_end": "",
      "wage": 0,
      "market_value": 0,
      "stats": {},
      "career": [],
      "training_focus": null,
      "transfer_listed": false,
      "loan_listed": false,
      "transfer_offers": [],
      "morale_core": {},
      "potential_base": 67,
      "potential_revealed": null,
      "potential_research_started_on": null,
      "potential_research_eta_days": null,
      "champion_training_targets": [],
      "can_be_transferred_until": null
    },
    {
      "id": "player-a03282a0",
      "match_name": "Neo",
      "full_name": "Neo",
      "date_of_birth": "2001-06-18",
      "nationality": "CL",
      "profile_image_url": null,
      "position": "JUNGLE",
      "natural_position": "JUNGLE",
      "alternate_positions": [],
      "attributes": {
        "laning": 65,
        "mechanics": 64,
        "discipline": 64,
        "macro_play": 64,
        "consistency": 65,
        "shotcalling": 62,
        "teamfighting": 62,
        "champion_pool": 62,
        "mental_resilience": 63
      },
      "condition": 100,
      "morale": 100,
      "fitness": 100,
      "team_id": "lrs-maze-gaming",
      "traits": [],
      "contract_end": "",
      "wage": 0,
      "market_value": 0,
      "stats": {},
      "career": [],
      "training_focus": null,
      "transfer_listed": false,
      "loan_listed": false,
      "transfer_offers": [],
      "morale_core": {},
      "potential_base": 67,
      "potential_revealed": null,
      "potential_research_started_on": null,
      "potential_research_eta_days": null,
      "champion_training_targets": [],
      "can_be_transferred_until": null
    },
    {
      "id": "player-cb8f7341",
      "match_name": "Nate",
      "full_name": "Nate",
      "date_of_birth": "2002-12-19",
      "nationality": "AR",
      "profile_image_url": null,
      "position": "TOP",
      "natural_position": "TOP",
      "alternate_positions": [],
      "attributes": {
        "laning": 62,
        "mechanics": 66,
        "discipline": 62,
        "macro_play": 63,
        "consistency": 64,
        "shotcalling": 62,
        "teamfighting": 65,
        "champion_pool": 63,
        "mental_resilience": 62
      },
      "condition": 100,
      "morale": 100,
      "fitness": 100,
      "team_id": "lrs-9z-globant",
      "traits": [],
      "contract_end": "",
      "wage": 0,
      "market_value": 0,
      "stats": {},
      "career": [],
      "training_focus": null,
      "transfer_listed": false,
      "loan_listed": false,
      "transfer_offers": [],
      "morale_core": {},
      "potential_base": 70,
      "potential_revealed": null,
      "potential_research_started_on": null,
      "potential_research_eta_days": null,
      "champion_training_targets": [],
      "can_be_transferred_until": null
    },
    {
      "id": "player-25aeb8b9",
      "match_name": "Venhamin",
      "full_name": "Venhamin",
      "date_of_birth": "1999-05-28",
      "nationality": "CL",
      "profile_image_url": null,
      "position": "TOP",
      "natural_position": "TOP",
      "alternate_positions": [],
      "attributes": {
        "laning": 62,
        "mechanics": 62,
        "discipline": 65,
        "macro_play": 62,
        "consistency": 62,
        "shotcalling": 62,
        "teamfighting": 62,
        "champion_pool": 62,
        "mental_resilience": 64
      },
      "condition": 100,
      "morale": 100,
      "fitness": 100,
      "team_id": "lrs-maze-gaming",
      "traits": [],
      "contract_end": "",
      "wage": 0,
      "market_value": 0,
      "stats": {},
      "career": [],
      "training_focus": null,
      "transfer_listed": false,
      "loan_listed": false,
      "transfer_offers": [],
      "morale_core": {},
      "potential_base": 64,
      "potential_revealed": null,
      "potential_research_started_on": null,
      "potential_research_eta_days": null,
      "champion_training_targets": [],
      "can_be_transferred_until": null
    },
    {
      "id": "player-da267bc9",
      "match_name": "Acce",
      "full_name": "Acce",
      "date_of_birth": "2004-05-17",
      "nationality": "AR",
      "profile_image_url": null,
      "position": "TOP",
      "natural_position": "TOP",
      "alternate_positions": [],
      "attributes": {
        "laning": 66,
        "mechanics": 64,
        "discipline": 65,
        "macro_play": 64,
        "consistency": 65,
        "shotcalling": 62,
        "teamfighting": 64,
        "champion_pool": 63,
        "mental_resilience": 64
      },
      "condition": 100,
      "morale": 100,
      "fitness": 100,
      "team_id": "lrs-the-new-kings",
      "traits": [],
      "contract_end": "",
      "wage": 0,
      "market_value": 0,
      "stats": {},
      "career": [],
      "training_focus": null,
      "transfer_listed": false,
      "loan_listed": false,
      "transfer_offers": [],
      "morale_core": {},
      "potential_base": 71,
      "potential_revealed": null,
      "potential_research_started_on": null,
      "potential_research_eta_days": null,
      "champion_training_targets": [],
      "can_be_transferred_until": null
    },
    {
      "id": "player-9b2246d8",
      "match_name": "Chordy",
      "full_name": "Chordy",
      "date_of_birth": "2000-07-22",
      "nationality": "AR",
      "profile_image_url": null,
      "position": "TOP",
      "natural_position": "TOP",
      "alternate_positions": [],
      "attributes": {
        "laning": 66,
        "mechanics": 66,
        "discipline": 66,
        "macro_play": 66,
        "consistency": 66,
        "shotcalling": 62,
        "teamfighting": 66,
        "champion_pool": 63,
        "mental_resilience": 66
      },
      "condition": 100,
      "morale": 100,
      "fitness": 100,
      "team_id": "lrs-volticons",
      "traits": [],
      "contract_end": "",
      "wage": 0,
      "market_value": 0,
      "stats": {},
      "career": [],
      "training_focus": null,
      "transfer_listed": false,
      "loan_listed": false,
      "transfer_offers": [],
      "morale_core": {},
      "potential_base": 68,
      "potential_revealed": null,
      "potential_research_started_on": null,
      "potential_research_eta_days": null,
      "champion_training_targets": [],
      "can_be_transferred_until": null
    },
    {
      "id": "player-9b95e2ec",
      "match_name": "AlluK",
      "full_name": "AlluK",
      "date_of_birth": "2005-01-28",
      "nationality": "AR",
      "profile_image_url": null,
      "position": "JUNGLE",
      "natural_position": "JUNGLE",
      "alternate_positions": [],
      "attributes": {
        "laning": 66,
        "mechanics": 66,
        "discipline": 58,
        "macro_play": 64,
        "consistency": 65,
        "shotcalling": 62,
        "teamfighting": 64,
        "champion_pool": 63,
        "mental_resilience": 62
      },
      "condition": 100,
      "morale": 100,
      "fitness": 100,
      "team_id": "lrs-malvinas-gaming",
      "traits": [],
      "contract_end": "",
      "wage": 0,
      "market_value": 0,
      "stats": {},
      "career": [],
      "training_focus": null,
      "transfer_listed": false,
      "loan_listed": false,
      "transfer_offers": [],
      "morale_core": {},
      "potential_base": 69,
      "potential_revealed": null,
      "potential_research_started_on": null,
      "potential_research_eta_days": null,
      "champion_training_targets": [],
      "can_be_transferred_until": null
    },
    {
      "id": "player-8d4d9b14",
      "match_name": "nvillada",
      "full_name": "nvillada",
      "date_of_birth": "2007-11-15",
      "nationality": "AR",
      "profile_image_url": null,
      "position": "TOP",
      "natural_position": "TOP",
      "alternate_positions": [],
      "attributes": {
        "laning": 63,
        "mechanics": 66,
        "discipline": 62,
        "macro_play": 64,
        "consistency": 65,
        "shotcalling": 62,
        "teamfighting": 65,
        "champion_pool": 63,
        "mental_resilience": 64
      },
      "condition": 100,
      "morale": 100,
      "fitness": 100,
      "team_id": "lrs-malvinas-gaming",
      "traits": [],
      "contract_end": "",
      "wage": 0,
      "market_value": 0,
      "stats": {},
      "career": [],
      "training_focus": null,
      "transfer_listed": false,
      "loan_listed": false,
      "transfer_offers": [],
      "morale_core": {},
      "potential_base": 72,
      "potential_revealed": null,
      "potential_research_started_on": null,
      "potential_research_eta_days": null,
      "champion_training_targets": [],
      "can_be_transferred_until": null
    },
    {
      "id": "player-eb8eb129",
      "match_name": "GianKios",
      "full_name": "GianKios",
      "date_of_birth": "2004-01-31",
      "nationality": "CL",
      "profile_image_url": null,
      "position": "TOP",
      "natural_position": "TOP",
      "alternate_positions": [],
      "attributes": {
        "laning": 66,
        "mechanics": 65,
        "discipline": 65,
        "macro_play": 66,
        "consistency": 66,
        "shotcalling": 62,
        "teamfighting": 66,
        "champion_pool": 62,
        "mental_resilience": 65
      },
      "condition": 100,
      "morale": 100,
      "fitness": 100,
      "team_id": "lrs-the-new-kings",
      "traits": [],
      "contract_end": "",
      "wage": 0,
      "market_value": 0,
      "stats": {},
      "career": [],
      "training_focus": null,
      "transfer_listed": false,
      "loan_listed": false,
      "transfer_offers": [],
      "morale_core": {},
      "potential_base": 65,
      "potential_revealed": null,
      "potential_research_started_on": null,
      "potential_research_eta_days": null,
      "champion_training_targets": [],
      "can_be_transferred_until": null
    },
    {
      "id": "player-64f74613",
      "match_name": "Pet",
      "full_name": "Pet",
      "date_of_birth": "2000-03-11",
      "nationality": "PE",
      "profile_image_url": null,
      "position": "TOP",
      "natural_position": "TOP",
      "alternate_positions": [],
      "attributes": {
        "laning": 66,
        "mechanics": 66,
        "discipline": 66,
        "macro_play": 66,
        "consistency": 66,
        "shotcalling": 62,
        "teamfighting": 66,
        "champion_pool": 63,
        "mental_resilience": 65
      },
      "condition": 100,
      "morale": 100,
      "fitness": 100,
      "team_id": "lrs-tu-pap-esports",
      "traits": [],
      "contract_end": "",
      "wage": 0,
      "market_value": 0,
      "stats": {},
      "career": [],
      "training_focus": null,
      "transfer_listed": false,
      "loan_listed": false,
      "transfer_offers": [],
      "morale_core": {},
      "potential_base": 66,
      "potential_revealed": null,
      "potential_research_started_on": null,
      "potential_research_eta_days": null,
      "champion_training_targets": [],
      "can_be_transferred_until": null
    },
    {
      "id": "player-996e3afc",
      "match_name": "Ganks",
      "full_name": "Ganks",
      "date_of_birth": "2000-03-12",
      "nationality": "PE",
      "profile_image_url": null,
      "position": "JUNGLE",
      "natural_position": "JUNGLE",
      "alternate_positions": [],
      "attributes": {
        "laning": 66,
        "mechanics": 66,
        "discipline": 60,
        "macro_play": 65,
        "consistency": 66,
        "shotcalling": 62,
        "teamfighting": 64,
        "champion_pool": 62,
        "mental_resilience": 62
      },
      "condition": 100,
      "morale": 100,
      "fitness": 100,
      "team_id": "lrs-golden-lions",
      "traits": [],
      "contract_end": "",
      "wage": 0,
      "market_value": 0,
      "stats": {},
      "career": [],
      "training_focus": null,
      "transfer_listed": false,
      "loan_listed": false,
      "transfer_offers": [],
      "morale_core": {},
      "potential_base": 67,
      "potential_revealed": null,
      "potential_research_started_on": null,
      "potential_research_eta_days": null,
      "champion_training_targets": [],
      "can_be_transferred_until": null
    },
    {
      "id": "player-c967059f",
      "match_name": "Cow",
      "full_name": "Cow",
      "date_of_birth": "2003-08-14",
      "nationality": "CL",
      "profile_image_url": null,
      "position": "JUNGLE",
      "natural_position": "JUNGLE",
      "alternate_positions": [],
      "attributes": {
        "laning": 64,
        "mechanics": 62,
        "discipline": 65,
        "macro_play": 62,
        "consistency": 63,
        "shotcalling": 62,
        "teamfighting": 62,
        "champion_pool": 63,
        "mental_resilience": 64
      },
      "condition": 100,
      "morale": 100,
      "fitness": 100,
      "team_id": "lrs-seven-dark",
      "traits": [],
      "contract_end": "",
      "wage": 0,
      "market_value": 0,
      "stats": {},
      "career": [],
      "training_focus": null,
      "transfer_listed": false,
      "loan_listed": false,
      "transfer_offers": [],
      "morale_core": {},
      "potential_base": 68,
      "potential_revealed": null,
      "potential_research_started_on": null,
      "potential_research_eta_days": null,
      "champion_training_targets": [],
      "can_be_transferred_until": null
    },
    {
      "id": "player-22ac81b4",
      "match_name": "Funky",
      "full_name": "Funky",
      "date_of_birth": "2003-04-24",
      "nationality": "AR",
      "profile_image_url": null,
      "position": "JUNGLE",
      "natural_position": "JUNGLE",
      "alternate_positions": [],
      "attributes": {
        "laning": 64,
        "mechanics": 64,
        "discipline": 66,
        "macro_play": 64,
        "consistency": 64,
        "shotcalling": 62,
        "teamfighting": 65,
        "champion_pool": 63,
        "mental_resilience": 66
      },
      "condition": 100,
      "morale": 100,
      "fitness": 100,
      "team_id": "lrs-the-new-kings",
      "traits": [],
      "contract_end": "",
      "wage": 0,
      "market_value": 0,
      "stats": {},
      "career": [],
      "training_focus": null,
      "transfer_listed": false,
      "loan_listed": false,
      "transfer_offers": [],
      "morale_core": {},
      "potential_base": 69,
      "potential_revealed": null,
      "potential_research_started_on": null,
      "potential_research_eta_days": null,
      "champion_training_targets": [],
      "can_be_transferred_until": null
    },
    {
      "id": "player-10d041d2",
      "match_name": "Warsor",
      "full_name": "Warsor",
      "date_of_birth": "2000-11-02",
      "nationality": "AR",
      "profile_image_url": null,
      "position": "JUNGLE",
      "natural_position": "JUNGLE",
      "alternate_positions": [],
      "attributes": {
        "laning": 65,
        "mechanics": 65,
        "discipline": 64,
        "macro_play": 66,
        "consistency": 66,
        "shotcalling": 62,
        "teamfighting": 66,
        "champion_pool": 62,
        "mental_resilience": 64
      },
      "condition": 100,
      "morale": 100,
      "fitness": 100,
      "team_id": "lrs-seven-dark",
      "traits": [],
      "contract_end": "",
      "wage": 0,
      "market_value": 0,
      "stats": {},
      "career": [],
      "training_focus": null,
      "transfer_listed": false,
      "loan_listed": false,
      "transfer_offers": [],
      "morale_core": {},
      "potential_base": 66,
      "potential_revealed": null,
      "potential_research_started_on": null,
      "potential_research_eta_days": null,
      "champion_training_targets": [],
      "can_be_transferred_until": null
    },
    {
      "id": "player-1c8c9a80",
      "match_name": "KinGi",
      "full_name": "KinGi",
      "date_of_birth": "2004-07-25",
      "nationality": "AR",
      "profile_image_url": null,
      "position": "JUNGLE",
      "natural_position": "JUNGLE",
      "alternate_positions": [],
      "attributes": {
        "laning": 65,
        "mechanics": 65,
        "discipline": 66,
        "macro_play": 65,
        "consistency": 65,
        "shotcalling": 62,
        "teamfighting": 66,
        "champion_pool": 62,
        "mental_resilience": 66
      },
      "condition": 100,
      "morale": 100,
      "fitness": 100,
      "team_id": "lrs-the-new-kings",
      "traits": [],
      "contract_end": "",
      "wage": 0,
      "market_value": 0,
      "stats": {},
      "career": [],
      "training_focus": null,
      "transfer_listed": false,
      "loan_listed": false,
      "transfer_offers": [],
      "morale_core": {},
      "potential_base": 72,
      "potential_revealed": null,
      "potential_research_started_on": null,
      "potential_research_eta_days": null,
      "champion_training_targets": [],
      "can_be_transferred_until": null
    },
    {
      "id": "player-3c95214c",
      "match_name": "Aloned",
      "full_name": "Aloned",
      "date_of_birth": "2003-11-17",
      "nationality": "CL",
      "profile_image_url": null,
      "position": "MID",
      "natural_position": "MID",
      "alternate_positions": [],
      "attributes": {
        "laning": 62,
        "mechanics": 64,
        "discipline": 62,
        "macro_play": 64,
        "consistency": 62,
        "shotcalling": 62,
        "teamfighting": 64,
        "champion_pool": 63,
        "mental_resilience": 63
      },
      "condition": 100,
      "morale": 100,
      "fitness": 100,
      "team_id": "lrs-9z-globant",
      "traits": [],
      "contract_end": "",
      "wage": 0,
      "market_value": 0,
      "stats": {},
      "career": [],
      "training_focus": null,
      "transfer_listed": false,
      "loan_listed": false,
      "transfer_offers": [],
      "morale_core": {},
      "potential_base": 68,
      "potential_revealed": null,
      "potential_research_started_on": null,
      "potential_research_eta_days": null,
      "champion_training_targets": [],
      "can_be_transferred_until": null
    },
    {
      "id": "player-9e4db75a",
      "match_name": "Hitsu",
      "full_name": "Hitsu",
      "date_of_birth": "2001-03-03",
      "nationality": "CL",
      "profile_image_url": null,
      "position": "MID",
      "natural_position": "MID",
      "alternate_positions": [],
      "attributes": {
        "laning": 64,
        "mechanics": 65,
        "discipline": 60,
        "macro_play": 62,
        "consistency": 63,
        "shotcalling": 62,
        "teamfighting": 65,
        "champion_pool": 61,
        "mental_resilience": 60
      },
      "condition": 100,
      "morale": 100,
      "fitness": 100,
      "team_id": "lrs-maze-gaming",
      "traits": [],
      "contract_end": "",
      "wage": 0,
      "market_value": 0,
      "stats": {},
      "career": [],
      "training_focus": null,
      "transfer_listed": false,
      "loan_listed": false,
      "transfer_offers": [],
      "morale_core": {},
      "potential_base": 63,
      "potential_revealed": null,
      "potential_research_started_on": null,
      "potential_research_eta_days": null,
      "champion_training_targets": [],
      "can_be_transferred_until": null
    },
    {
      "id": "player-780c1a54",
      "match_name": "Kiefer",
      "full_name": "Kiefer",
      "date_of_birth": "2002-11-28",
      "nationality": "CL",
      "profile_image_url": null,
      "position": "MID",
      "natural_position": "MID",
      "alternate_positions": [],
      "attributes": {
        "laning": 64,
        "mechanics": 62,
        "discipline": 62,
        "macro_play": 61,
        "consistency": 63,
        "shotcalling": 60,
        "teamfighting": 62,
        "champion_pool": 60,
        "mental_resilience": 63
      },
      "condition": 100,
      "morale": 100,
      "fitness": 100,
      "team_id": "lrs-the-new-kings",
      "traits": [],
      "contract_end": "",
      "wage": 0,
      "market_value": 0,
      "stats": {},
      "career": [],
      "training_focus": null,
      "transfer_listed": false,
      "loan_listed": false,
      "transfer_offers": [],
      "morale_core": {},
      "potential_base": 65,
      "potential_revealed": null,
      "potential_research_started_on": null,
      "potential_research_eta_days": null,
      "champion_training_targets": [],
      "can_be_transferred_until": null
    },
    {
      "id": "player-699bedbb",
      "match_name": "Gus",
      "full_name": "Gus",
      "date_of_birth": "1998-03-14",
      "nationality": "PE",
      "profile_image_url": null,
      "position": "MID",
      "natural_position": "MID",
      "alternate_positions": [],
      "attributes": {
        "laning": 64,
        "mechanics": 64,
        "discipline": 64,
        "macro_play": 64,
        "consistency": 64,
        "shotcalling": 60,
        "teamfighting": 64,
        "champion_pool": 61,
        "mental_resilience": 64
      },
      "condition": 100,
      "morale": 100,
      "fitness": 100,
      "team_id": "lrs-tu-pap-esports",
      "traits": [],
      "contract_end": "",
      "wage": 0,
      "market_value": 0,
      "stats": {},
      "career": [],
      "training_focus": null,
      "transfer_listed": false,
      "loan_listed": false,
      "transfer_offers": [],
      "morale_core": {},
      "potential_base": 64,
      "potential_revealed": null,
      "potential_research_started_on": null,
      "potential_research_eta_days": null,
      "champion_training_targets": [],
      "can_be_transferred_until": null
    },
    {
      "id": "player-ea7a190e",
      "match_name": "Strensh",
      "full_name": "Strensh",
      "date_of_birth": "2004-10-01",
      "nationality": "CL",
      "profile_image_url": null,
      "position": "ADC",
      "natural_position": "ADC",
      "alternate_positions": [],
      "attributes": {
        "laning": 55,
        "mechanics": 56,
        "discipline": 52,
        "macro_play": 56,
        "consistency": 56,
        "shotcalling": 52,
        "teamfighting": 55,
        "champion_pool": 53,
        "mental_resilience": 54
      },
      "condition": 100,
      "morale": 100,
      "fitness": 100,
      "team_id": "lrs-golden-lions",
      "traits": [],
      "contract_end": "",
      "wage": 0,
      "market_value": 0,
      "stats": {},
      "career": [],
      "training_focus": null,
      "transfer_listed": false,
      "loan_listed": false,
      "transfer_offers": [],
      "morale_core": {},
      "potential_base": 59,
      "potential_revealed": null,
      "potential_research_started_on": null,
      "potential_research_eta_days": null,
      "champion_training_targets": [],
      "can_be_transferred_until": null
    },
    {
      "id": "player-f1b49cb8",
      "match_name": "Coow",
      "full_name": "Coow",
      "date_of_birth": "1999-10-30",
      "nationality": "CL",
      "profile_image_url": null,
      "position": "JUNGLE",
      "natural_position": "JUNGLE",
      "alternate_positions": [],
      "attributes": {
        "laning": 64,
        "mechanics": 64,
        "discipline": 65,
        "macro_play": 64,
        "consistency": 64,
        "shotcalling": 62,
        "teamfighting": 63,
        "champion_pool": 61,
        "mental_resilience": 65
      },
      "condition": 100,
      "morale": 100,
      "fitness": 100,
      "team_id": "lrs-the-new-kings",
      "traits": [],
      "contract_end": "",
      "wage": 0,
      "market_value": 0,
      "stats": {},
      "career": [],
      "training_focus": null,
      "transfer_listed": false,
      "loan_listed": false,
      "transfer_offers": [],
      "morale_core": {},
      "potential_base": 65,
      "potential_revealed": null,
      "potential_research_started_on": null,
      "potential_research_eta_days": null,
      "champion_training_targets": [],
      "can_be_transferred_until": null
    },
    {
      "id": "player-06c8e1c7",
      "match_name": "Mitir",
      "full_name": "Mitir",
      "date_of_birth": "2002-12-24",
      "nationality": "CO",
      "profile_image_url": null,
      "position": "JUNGLE",
      "natural_position": "JUNGLE",
      "alternate_positions": [],
      "attributes": {
        "laning": 66,
        "mechanics": 66,
        "discipline": 66,
        "macro_play": 66,
        "consistency": 66,
        "shotcalling": 63,
        "teamfighting": 66,
        "champion_pool": 63,
        "mental_resilience": 66
      },
      "condition": 100,
      "morale": 100,
      "fitness": 100,
      "team_id": "lrs-tu-pap-esports",
      "traits": [],
      "contract_end": "",
      "wage": 0,
      "market_value": 0,
      "stats": {},
      "career": [],
      "training_focus": null,
      "transfer_listed": false,
      "loan_listed": false,
      "transfer_offers": [],
      "morale_core": {},
      "potential_base": 69,
      "potential_revealed": null,
      "potential_research_started_on": null,
      "potential_research_eta_days": null,
      "champion_training_targets": [],
      "can_be_transferred_until": null
    },
    {
      "id": "player-bd6a1e79",
      "match_name": "Saifer",
      "full_name": "Saifer",
      "date_of_birth": "2003-07-27",
      "nationality": "AR",
      "profile_image_url": null,
      "position": "MID",
      "natural_position": "MID",
      "alternate_positions": [],
      "attributes": {
        "laning": 62,
        "mechanics": 65,
        "discipline": 58,
        "macro_play": 65,
        "consistency": 63,
        "shotcalling": 62,
        "teamfighting": 62,
        "champion_pool": 62,
        "mental_resilience": 62
      },
      "condition": 100,
      "morale": 100,
      "fitness": 100,
      "team_id": "lrs-golden-lions",
      "traits": [],
      "contract_end": "",
      "wage": 0,
      "market_value": 0,
      "stats": {},
      "career": [],
      "training_focus": null,
      "transfer_listed": false,
      "loan_listed": false,
      "transfer_offers": [],
      "morale_core": {},
      "potential_base": 66,
      "potential_revealed": null,
      "potential_research_started_on": null,
      "potential_research_eta_days": null,
      "champion_training_targets": [],
      "can_be_transferred_until": null
    },
    {
      "id": "player-cec97cd4",
      "match_name": "Neadz",
      "full_name": "Neadz",
      "date_of_birth": "2005-03-26",
      "nationality": "CL",
      "profile_image_url": null,
      "position": "MID",
      "natural_position": "MID",
      "alternate_positions": [],
      "attributes": {
        "laning": 60,
        "mechanics": 58,
        "discipline": 56,
        "macro_play": 58,
        "consistency": 60,
        "shotcalling": 56,
        "teamfighting": 58,
        "champion_pool": 56,
        "mental_resilience": 58
      },
      "condition": 100,
      "morale": 100,
      "fitness": 100,
      "team_id": "lrs-seven-dark",
      "traits": [],
      "contract_end": "",
      "wage": 0,
      "market_value": 0,
      "stats": {},
      "career": [],
      "training_focus": null,
      "transfer_listed": false,
      "loan_listed": false,
      "transfer_offers": [],
      "morale_core": {},
      "potential_base": 63,
      "potential_revealed": null,
      "potential_research_started_on": null,
      "potential_research_eta_days": null,
      "champion_training_targets": [],
      "can_be_transferred_until": null
    },
    {
      "id": "player-9d05fb48",
      "match_name": "SkyMind",
      "full_name": "SkyMind",
      "date_of_birth": "1999-03-01",
      "nationality": "CL",
      "profile_image_url": null,
      "position": "MID",
      "natural_position": "MID",
      "alternate_positions": [],
      "attributes": {
        "laning": 64,
        "mechanics": 65,
        "discipline": 64,
        "macro_play": 65,
        "consistency": 64,
        "shotcalling": 62,
        "teamfighting": 64,
        "champion_pool": 63,
        "mental_resilience": 65
      },
      "condition": 100,
      "morale": 100,
      "fitness": 100,
      "team_id": "lrs-the-new-kings",
      "traits": [],
      "contract_end": "",
      "wage": 0,
      "market_value": 0,
      "stats": {},
      "career": [],
      "training_focus": null,
      "transfer_listed": false,
      "loan_listed": false,
      "transfer_offers": [],
      "morale_core": {},
      "potential_base": 65,
      "potential_revealed": null,
      "potential_research_started_on": null,
      "potential_research_eta_days": null,
      "champion_training_targets": [],
      "can_be_transferred_until": null
    },
    {
      "id": "player-dff39ab1",
      "match_name": "DiDi",
      "full_name": "DiDi",
      "date_of_birth": "1996-05-07",
      "nationality": "AR",
      "profile_image_url": null,
      "position": "MID",
      "natural_position": "MID",
      "alternate_positions": [],
      "attributes": {
        "laning": 66,
        "mechanics": 66,
        "discipline": 66,
        "macro_play": 66,
        "consistency": 66,
        "shotcalling": 62,
        "teamfighting": 66,
        "champion_pool": 63,
        "mental_resilience": 66
      },
      "condition": 100,
      "morale": 100,
      "fitness": 100,
      "team_id": "lrs-volticons",
      "traits": [],
      "contract_end": "",
      "wage": 0,
      "market_value": 0,
      "stats": {},
      "career": [],
      "training_focus": null,
      "transfer_listed": false,
      "loan_listed": false,
      "transfer_offers": [],
      "morale_core": {},
      "potential_base": 66,
      "potential_revealed": null,
      "potential_research_started_on": null,
      "potential_research_eta_days": null,
      "champion_training_targets": [],
      "can_be_transferred_until": null
    },
    {
      "id": "player-a0616e7b",
      "match_name": "Martote",
      "full_name": "Martote",
      "date_of_birth": "2003-09-23",
      "nationality": "UY",
      "profile_image_url": null,
      "position": "JUNGLE",
      "natural_position": "JUNGLE",
      "alternate_positions": [],
      "attributes": {
        "laning": 66,
        "mechanics": 66,
        "discipline": 66,
        "macro_play": 66,
        "consistency": 66,
        "shotcalling": 62,
        "teamfighting": 66,
        "champion_pool": 63,
        "mental_resilience": 66
      },
      "condition": 100,
      "morale": 100,
      "fitness": 100,
      "team_id": "lrs-volticons",
      "traits": [],
      "contract_end": "",
      "wage": 0,
      "market_value": 0,
      "stats": {},
      "career": [],
      "training_focus": null,
      "transfer_listed": false,
      "loan_listed": false,
      "transfer_offers": [],
      "morale_core": {},
      "potential_base": 69,
      "potential_revealed": null,
      "potential_research_started_on": null,
      "potential_research_eta_days": null,
      "champion_training_targets": [],
      "can_be_transferred_until": null
    },
    {
      "id": "player-4bb1af95",
      "match_name": "Nobody",
      "full_name": "Nobody",
      "date_of_birth": "2000-07-22",
      "nationality": "AR",
      "profile_image_url": null,
      "position": "MID",
      "natural_position": "MID",
      "alternate_positions": [],
      "attributes": {
        "laning": 65,
        "mechanics": 66,
        "discipline": 62,
        "macro_play": 66,
        "consistency": 65,
        "shotcalling": 62,
        "teamfighting": 63,
        "champion_pool": 63,
        "mental_resilience": 64
      },
      "condition": 100,
      "morale": 100,
      "fitness": 100,
      "team_id": "lrs-malvinas-gaming",
      "traits": [],
      "contract_end": "",
      "wage": 0,
      "market_value": 0,
      "stats": {},
      "career": [],
      "training_focus": null,
      "transfer_listed": false,
      "loan_listed": false,
      "transfer_offers": [],
      "morale_core": {},
      "potential_base": 69,
      "potential_revealed": null,
      "potential_research_started_on": null,
      "potential_research_eta_days": null,
      "champion_training_targets": [],
      "can_be_transferred_until": null
    },
    {
      "id": "player-038a68be",
      "match_name": "Peco",
      "full_name": "Peco",
      "date_of_birth": "2003-08-03",
      "nationality": "BR",
      "profile_image_url": null,
      "position": "MID",
      "natural_position": "MID",
      "alternate_positions": [],
      "attributes": {
        "laning": 56,
        "mechanics": 54,
        "discipline": 54,
        "macro_play": 54,
        "consistency": 56,
        "shotcalling": 50,
        "teamfighting": 56,
        "champion_pool": 52,
        "mental_resilience": 54
      },
      "condition": 100,
      "morale": 100,
      "fitness": 100,
      "team_id": "lrs-seven-dark",
      "traits": [],
      "contract_end": "",
      "wage": 0,
      "market_value": 0,
      "stats": {},
      "career": [],
      "training_focus": null,
      "transfer_listed": false,
      "loan_listed": false,
      "transfer_offers": [],
      "morale_core": {},
      "potential_base": 57,
      "potential_revealed": null,
      "potential_research_started_on": null,
      "potential_research_eta_days": null,
      "champion_training_targets": [],
      "can_be_transferred_until": null
    },
    {
      "id": "player-57ce3cc5",
      "match_name": "Galileo",
      "full_name": "Galileo",
      "date_of_birth": "2001-01-30",
      "nationality": "PE",
      "profile_image_url": null,
      "position": "MID",
      "natural_position": "MID",
      "alternate_positions": [],
      "attributes": {
        "laning": 56,
        "mechanics": 54,
        "discipline": 56,
        "macro_play": 54,
        "consistency": 55,
        "shotcalling": 52,
        "teamfighting": 54,
        "champion_pool": 53,
        "mental_resilience": 56
      },
      "condition": 100,
      "morale": 100,
      "fitness": 100,
      "team_id": "lrs-tu-pap-esports",
      "traits": [],
      "contract_end": "",
      "wage": 0,
      "market_value": 0,
      "stats": {},
      "career": [],
      "training_focus": null,
      "transfer_listed": false,
      "loan_listed": false,
      "transfer_offers": [],
      "morale_core": {},
      "potential_base": 55,
      "potential_revealed": null,
      "potential_research_started_on": null,
      "potential_research_eta_days": null,
      "champion_training_targets": [],
      "can_be_transferred_until": null
    },
    {
      "id": "player-87a26a18",
      "match_name": "Fix",
      "full_name": "Fix",
      "date_of_birth": "2002-06-02",
      "nationality": "AR",
      "profile_image_url": null,
      "position": "ADC",
      "natural_position": "ADC",
      "alternate_positions": [],
      "attributes": {
        "laning": 50,
        "mechanics": 53,
        "discipline": 54,
        "macro_play": 48,
        "consistency": 48,
        "shotcalling": 52,
        "teamfighting": 53,
        "champion_pool": 53,
        "mental_resilience": 53
      },
      "condition": 100,
      "morale": 100,
      "fitness": 100,
      "team_id": "lrs-9z-globant",
      "traits": [],
      "contract_end": "",
      "wage": 0,
      "market_value": 0,
      "stats": {},
      "career": [],
      "training_focus": null,
      "transfer_listed": false,
      "loan_listed": false,
      "transfer_offers": [],
      "morale_core": {},
      "potential_base": 55,
      "potential_revealed": null,
      "potential_research_started_on": null,
      "potential_research_eta_days": null,
      "champion_training_targets": [],
      "can_be_transferred_until": null
    },
    {
      "id": "player-7b7cb20f",
      "match_name": "Coscu",
      "full_name": "Coscu",
      "date_of_birth": null,
      "nationality": "AR",
      "profile_image_url": null,
      "position": "SUPPORT",
      "natural_position": "SUPPORT",
      "alternate_positions": [],
      "attributes": {
        "laning": 51,
        "mechanics": 50,
        "discipline": 59,
        "macro_play": 50,
        "consistency": 54,
        "shotcalling": 56,
        "teamfighting": 50,
        "champion_pool": 52,
        "mental_resilience": 55
      },
      "condition": 100,
      "morale": 100,
      "fitness": 100,
      "team_id": "lrs-9z-globant",
      "traits": [],
      "contract_end": null,
      "wage": 50000,
      "market_value": 750000,
      "stats": {},
      "career": [],
      "training_focus": null,
      "transfer_listed": false,
      "loan_listed": false,
      "transfer_offers": [],
      "morale_core": {},
      "potential_base": 99,
      "potential_revealed": null,
      "potential_research_started_on": null,
      "potential_research_eta_days": null,
      "champion_training_targets": [],
      "can_be_transferred_until": null
    },
    {
      "id": "player-364f0667",
      "match_name": "Fortu",
      "full_name": "Fortu",
      "date_of_birth": null,
      "nationality": "AR",
      "profile_image_url": null,
      "position": "SUPPORT",
      "natural_position": "SUPPORT",
      "alternate_positions": [],
      "attributes": {
        "laning": 55,
        "mechanics": 56,
        "discipline": 53,
        "macro_play": 55,
        "consistency": 56,
        "shotcalling": 52,
        "teamfighting": 55,
        "champion_pool": 53,
        "mental_resilience": 54
      },
      "condition": 100,
      "morale": 100,
      "fitness": 100,
      "team_id": "lrs-malvinas-gaming",
      "traits": [],
      "contract_end": null,
      "wage": 50000,
      "market_value": 750000,
      "stats": {},
      "career": [],
      "training_focus": null,
      "transfer_listed": false,
      "loan_listed": false,
      "transfer_offers": [],
      "morale_core": {},
      "potential_base": 99,
      "potential_revealed": null,
      "potential_research_started_on": null,
      "potential_research_eta_days": null,
      "champion_training_targets": [],
      "can_be_transferred_until": null
    },
    {
      "id": "player-472111f6",
      "match_name": "Pyl",
      "full_name": "Pyl",
      "date_of_birth": null,
      "nationality": "CL",
      "profile_image_url": null,
      "position": "SUPPORT",
      "natural_position": "SUPPORT",
      "alternate_positions": [],
      "attributes": {
        "laning": 53,
        "mechanics": 54,
        "discipline": 55,
        "macro_play": 55,
        "consistency": 55,
        "shotcalling": 52,
        "teamfighting": 53,
        "champion_pool": 52,
        "mental_resilience": 55
      },
      "condition": 100,
      "morale": 100,
      "fitness": 100,
      "team_id": "lrs-seven-dark",
      "traits": [],
      "contract_end": null,
      "wage": 50000,
      "market_value": 750000,
      "stats": {},
      "career": [],
      "training_focus": null,
      "transfer_listed": false,
      "loan_listed": false,
      "transfer_offers": [],
      "morale_core": {},
      "potential_base": 99,
      "potential_revealed": null,
      "potential_research_started_on": null,
      "potential_research_eta_days": null,
      "champion_training_targets": [],
      "can_be_transferred_until": null
    },
    {
      "id": "player-b6696d36",
      "match_name": "Iska",
      "full_name": "Iska",
      "date_of_birth": null,
      "nationality": "PE",
      "profile_image_url": null,
      "position": "SUPPORT",
      "natural_position": "SUPPORT",
      "alternate_positions": [],
      "attributes": {
        "laning": 55,
        "mechanics": 55,
        "discipline": 56,
        "macro_play": 55,
        "consistency": 55,
        "shotcalling": 52,
        "teamfighting": 55,
        "champion_pool": 53,
        "mental_resilience": 55
      },
      "condition": 100,
      "morale": 100,
      "fitness": 100,
      "team_id": "lrs-tu-pap-esports",
      "traits": [],
      "contract_end": null,
      "wage": 50000,
      "market_value": 750000,
      "stats": {},
      "career": [],
      "training_focus": null,
      "transfer_listed": false,
      "loan_listed": false,
      "transfer_offers": [],
      "morale_core": {},
      "potential_base": 99,
      "potential_revealed": null,
      "potential_research_started_on": null,
      "potential_research_eta_days": null,
      "champion_training_targets": [],
      "can_be_transferred_until": null
    },
    {
      "id": "player-3004a953",
      "match_name": "Uxie",
      "full_name": "Uxie",
      "date_of_birth": null,
      "nationality": "AR",
      "profile_image_url": null,
      "position": "SUPPORT",
      "natural_position": "SUPPORT",
      "alternate_positions": [],
      "attributes": {
        "laning": 54,
        "mechanics": 58,
        "discipline": 56,
        "macro_play": 58,
        "consistency": 59,
        "shotcalling": 56,
        "teamfighting": 54,
        "champion_pool": 55,
        "mental_resilience": 56
      },
      "condition": 100,
      "morale": 100,
      "fitness": 100,
      "team_id": "lrs-9z-globant",
      "traits": [],
      "contract_end": null,
      "wage": 50000,
      "market_value": 750000,
      "stats": {},
      "career": [],
      "training_focus": null,
      "transfer_listed": false,
      "loan_listed": false,
      "transfer_offers": [],
      "morale_core": {},
      "potential_base": 99,
      "potential_revealed": null,
      "potential_research_started_on": null,
      "potential_research_eta_days": null,
      "champion_training_targets": [],
      "can_be_transferred_until": null
    },
    {
      "id": "player-063bc234",
      "match_name": "CHK",
      "full_name": "CHK",
      "date_of_birth": null,
      "nationality": "AR",
      "profile_image_url": null,
      "position": "SUPPORT",
      "natural_position": "SUPPORT",
      "alternate_positions": [],
      "attributes": {
        "laning": 58,
        "mechanics": 59,
        "discipline": 57,
        "macro_play": 56,
        "consistency": 56,
        "shotcalling": 56,
        "teamfighting": 59,
        "champion_pool": 55,
        "mental_resilience": 56
      },
      "condition": 100,
      "morale": 100,
      "fitness": 100,
      "team_id": "lrs-maze-gaming",
      "traits": [],
      "contract_end": null,
      "wage": 50000,
      "market_value": 750000,
      "stats": {},
      "career": [],
      "training_focus": null,
      "transfer_listed": false,
      "loan_listed": false,
      "transfer_offers": [],
      "morale_core": {},
      "potential_base": 99,
      "potential_revealed": null,
      "potential_research_started_on": null,
      "potential_research_eta_days": null,
      "champion_training_targets": [],
      "can_be_transferred_until": null
    },
    {
      "id": "player-7409e684",
      "match_name": "Stoneses",
      "full_name": "Stoneses",
      "date_of_birth": null,
      "nationality": "BR",
      "profile_image_url": null,
      "position": "SUPPORT",
      "natural_position": "SUPPORT",
      "alternate_positions": [],
      "attributes": {
        "laning": 63,
        "mechanics": 64,
        "discipline": 62,
        "macro_play": 63,
        "consistency": 63,
        "shotcalling": 59,
        "teamfighting": 62,
        "champion_pool": 60,
        "mental_resilience": 63
      },
      "condition": 100,
      "morale": 100,
      "fitness": 100,
      "team_id": "lrs-seven-dark",
      "traits": [],
      "contract_end": null,
      "wage": 50000,
      "market_value": 750000,
      "stats": {},
      "career": [],
      "training_focus": null,
      "transfer_listed": false,
      "loan_listed": false,
      "transfer_offers": [],
      "morale_core": {},
      "potential_base": 99,
      "potential_revealed": null,
      "potential_research_started_on": null,
      "potential_research_eta_days": null,
      "champion_training_targets": [],
      "can_be_transferred_until": null
    },
    {
      "id": "player-6fc2ebc1",
      "match_name": "Maximo",
      "full_name": "Maximo",
      "date_of_birth": null,
      "nationality": "AR",
      "profile_image_url": null,
      "position": "SUPPORT",
      "natural_position": "SUPPORT",
      "alternate_positions": [],
      "attributes": {
        "laning": 60,
        "mechanics": 60,
        "discipline": 60,
        "macro_play": 60,
        "consistency": 60,
        "shotcalling": 56,
        "teamfighting": 60,
        "champion_pool": 57,
        "mental_resilience": 60
      },
      "condition": 100,
      "morale": 100,
      "fitness": 100,
      "team_id": "lrs-tu-pap-esports",
      "traits": [],
      "contract_end": null,
      "wage": 50000,
      "market_value": 750000,
      "stats": {},
      "career": [],
      "training_focus": null,
      "transfer_listed": false,
      "loan_listed": false,
      "transfer_offers": [],
      "morale_core": {},
      "potential_base": 99,
      "potential_revealed": null,
      "potential_research_started_on": null,
      "potential_research_eta_days": null,
      "champion_training_targets": [],
      "can_be_transferred_until": null
    },
    {
      "id": "player-8c9a6b4a",
      "match_name": "Ux",
      "full_name": "Ux",
      "date_of_birth": null,
      "nationality": "AR",
      "profile_image_url": null,
      "position": "SUPPORT",
      "natural_position": "SUPPORT",
      "alternate_positions": [],
      "attributes": {
        "laning": 58,
        "mechanics": 59,
        "discipline": 64,
        "macro_play": 61,
        "consistency": 56,
        "shotcalling": 60,
        "teamfighting": 61,
        "champion_pool": 59,
        "mental_resilience": 62
      },
      "condition": 100,
      "morale": 100,
      "fitness": 100,
      "team_id": "lrs-9z-globant",
      "traits": [],
      "contract_end": null,
      "wage": 50000,
      "market_value": 750000,
      "stats": {},
      "career": [],
      "training_focus": null,
      "transfer_listed": false,
      "loan_listed": false,
      "transfer_offers": [],
      "morale_core": {},
      "potential_base": 99,
      "potential_revealed": null,
      "potential_research_started_on": null,
      "potential_research_eta_days": null,
      "champion_training_targets": [],
      "can_be_transferred_until": null
    },
    {
      "id": "player-0e47e371",
      "match_name": "Gastruks",
      "full_name": "Gastruks",
      "date_of_birth": null,
      "nationality": "AR",
      "profile_image_url": null,
      "position": "SUPPORT",
      "natural_position": "SUPPORT",
      "alternate_positions": [],
      "attributes": {
        "laning": 62,
        "mechanics": 64,
        "discipline": 58,
        "macro_play": 63,
        "consistency": 64,
        "shotcalling": 60,
        "teamfighting": 63,
        "champion_pool": 61,
        "mental_resilience": 60
      },
      "condition": 100,
      "morale": 100,
      "fitness": 100,
      "team_id": "lrs-golden-lions",
      "traits": [],
      "contract_end": null,
      "wage": 50000,
      "market_value": 750000,
      "stats": {},
      "career": [],
      "training_focus": null,
      "transfer_listed": false,
      "loan_listed": false,
      "transfer_offers": [],
      "morale_core": {},
      "potential_base": 99,
      "potential_revealed": null,
      "potential_research_started_on": null,
      "potential_research_eta_days": null,
      "champion_training_targets": [],
      "can_be_transferred_until": null
    },
    {
      "id": "player-80ab7e4f",
      "match_name": "Makishy",
      "full_name": "Makishy",
      "date_of_birth": null,
      "nationality": "CL",
      "profile_image_url": null,
      "position": "SUPPORT",
      "natural_position": "SUPPORT",
      "alternate_positions": [],
      "attributes": {
        "laning": 63,
        "mechanics": 63,
        "discipline": 64,
        "macro_play": 64,
        "consistency": 63,
        "shotcalling": 60,
        "teamfighting": 64,
        "champion_pool": 60,
        "mental_resilience": 63
      },
      "condition": 100,
      "morale": 100,
      "fitness": 100,
      "team_id": "lrs-maze-gaming",
      "traits": [],
      "contract_end": null,
      "wage": 50000,
      "market_value": 750000,
      "stats": {},
      "career": [],
      "training_focus": null,
      "transfer_listed": false,
      "loan_listed": false,
      "transfer_offers": [],
      "morale_core": {},
      "potential_base": 99,
      "potential_revealed": null,
      "potential_research_started_on": null,
      "potential_research_eta_days": null,
      "champion_training_targets": [],
      "can_be_transferred_until": null
    },
    {
      "id": "player-efe25219",
      "match_name": "Camilo",
      "full_name": "Camilo",
      "date_of_birth": null,
      "nationality": "UY",
      "profile_image_url": null,
      "position": "SUPPORT",
      "natural_position": "SUPPORT",
      "alternate_positions": [],
      "attributes": {
        "laning": 56,
        "mechanics": 56,
        "discipline": 56,
        "macro_play": 56,
        "consistency": 56,
        "shotcalling": 52,
        "teamfighting": 56,
        "champion_pool": 53,
        "mental_resilience": 56
      },
      "condition": 100,
      "morale": 100,
      "fitness": 100,
      "team_id": "lrs-volticons",
      "traits": [],
      "contract_end": null,
      "wage": 50000,
      "market_value": 750000,
      "stats": {},
      "career": [],
      "training_focus": null,
      "transfer_listed": false,
      "loan_listed": false,
      "transfer_offers": [],
      "morale_core": {},
      "potential_base": 99,
      "potential_revealed": null,
      "potential_research_started_on": null,
      "potential_research_eta_days": null,
      "champion_training_targets": [],
      "can_be_transferred_until": null
    }
  ]
}